[1,["ecpdLyjvZBwrvm+cedCcQy","90U/En4j5D/rwpD+TfcY2Y","51wLR0dhJBiqzgQZpIb2aB","20vVlN3p9DCpi417pqwspr","67ksGoIPdNIrFk9nYSyevO"],["node","_spriteFrame","_textureSetter","lbProgress","scene","_parent"],[["cc.Node",["_name","_id","_components","_contentSize","_parent","_children","_trs"],1,9,5,1,2,7],["cc.Sprite",["_sizeMode","_isTrimmedMode","_type","node","_materials","_spriteFrame"],0,1,3,6],["cc.Widget",["_alignFlags","_left","_right","_top","_bottom","_originalHeight","node"],-3,1],"cc.SpriteFrame",["cc.SceneAsset",["_name","asyncLoadAssets"],1],["cc.Node",["_name","_parent","_components","_contentSize","_trs"],2,1,2,5,7],["cc.Canvas",["_fitWidth","_fitHeight","node","_designResolution"],1,1,5],["f8a796I44tOP7in+xSPSaiw",["node","lbProgress"],3,1,1],["cc.Layout",["_resize","_N$layoutType","_N$spacingX","node","_layoutSize"],0,1,5],["cc.Scene",["_name","_active","_children","_anchorPoint","_trs"],1,2,5,7],["cc.Camera",["_clearFlags","_depth","node"],1,1],["41deehQFiRAjpsM62X8dHQP",["_string","_N$verticalAlign","node","_materials"],1,1,3],["cc.Label",["_string","_N$horizontalAlign","_N$verticalAlign","node","_materials"],0,1,3]],[[0,0,4,2,3,6,2],[4,0,1,3],[0,0,1,5,2,3,6,3],[0,0,4,5,2,3,2],[0,0,4,5,2,3,6,2],[0,0,4,2,2],[0,0,4,2,3,2],[5,0,1,2,3,4,2],[6,0,1,2,3,3],[7,0,1,1],[2,0,6,2],[2,0,1,2,3,4,5,6,7],[1,2,0,1,3,4,5,4],[1,0,1,3,4,5,3],[1,3,4,5,1],[8,0,1,2,3,4,4],[9,0,1,2,3,4,3],[10,0,1,2,3],[11,0,1,2,3,3],[12,0,1,2,3,4,4]],[[[{"name":"6","rect":[0,0,3500,2000],"offset":[0,0],"originalSize":[3500,2000],"capInsets":[0,0,0,0]}],[3],0,[0],[2],[1]],[[[1,"startScene",null],[2,"Canvas","ec94TBYaFIYqH+fK1ZJfuI",[-5,-6,-7],[[8,true,false,-1,[5,720,1280]],[9,-3,-2],[10,45,-4]],[5,720,1280],[360,640,0,0,0,0,1,1,1,1]],[3,"bg",1,[-10,-11],[[12,2,0,false,-8,[4],5],[11,45,-36,-36,-116,-116,1600,-9]],[5,792,1512]],[4,"progress",1,[-13,-14],[[15,1,1,5,-12,[5,62.82,80]]],[5,62.82,80],[0,-150,0,0,0,0,1,1,1,1]],[16,"New Node",false,[1],[0,0,0],[0,0,0,0,0,0,1,1,1,1]],[5,"Main Camera",1,[[17,7,-1,-15]]],[0,"commonImg01",2,[[13,2,false,-16,[0],1]],[5,230,512],[0,0,0,0,0,0,1,3.2,3.2,1]],[6,"logo",2,[[14,-17,[2],3]],[5,3500,2000]],[7,"txtProgress",3,[-18],[5,22.25,50.4],[-20.284999999999997,0,0,0,0,0,1,1,1,1]],[18,"1",1,8,[6]],[0,"percent",3,[[19,"%",1,1,-19,[7]]],[5,35.57,50.4],[13.625000000000004,0,0,0,0,0,1,1,1,1]]],0,[0,0,1,0,3,9,0,0,1,0,0,1,0,-1,5,0,-2,2,0,-3,3,0,0,2,0,0,2,0,-1,6,0,-2,7,0,0,3,0,-1,8,0,-2,10,0,0,5,0,0,6,0,0,7,0,-1,9,0,0,10,0,4,4,1,5,4,19],[0,0,0,0,0,0,0,0],[-1,1,-1,1,-1,1,-1,-1],[0,2,0,3,0,4,0,0]]]]