[{"__type__":"cc.SpriteFrame","content":{"name":"tgadv_btn_morgame_bg","texture":"18cd98d80","rect":[231,603,128,125],"offset":[0,0],"originalSize":[128,125],"rotated":1,"capInsets":[0,0,0,0]}},{"__type__":"cc.SpriteFrame","content":{"name":"default_btn_disabled","texture":"71VhFCTINJM6/Ky3oX9nBT","rect":[0,0,40,40],"offset":[0,0],"originalSize":[40,40],"capInsets":[12,12,12,12]}},[{"__type__":"cc.Prefab","_name":"TgBanner","data":{"__id__":1}},{"__type__":"cc.Node","_name":"TgBanner","_children":[{"__id__":2},{"__id__":3},{"__id__":6},{"__id__":7}],"_components":[{"__type__":"cc.Widget","node":{"__id__":1},"_alignFlags":9,"_right":360,"_originalHeight":150},{"__type__":"cc.BlockInputEvents","node":{"__id__":1},"_enabled":false},{"__type__":"fbc220oTsNDQZtHkoz6kYr/","node":{"__id__":1},"AdvRoot":{"__id__":6},"AdvItem":{"__id__":3},"Img_Bg":{"__id__":2},"MoreGame":{"__id__":7}}],"_prefab":{"__type__":"cc.PrefabInfo","root":{"__id__":1},"asset":{"__uuid__":"55aI6lczxJ/6HqSUdQOiZL"},"fileId":"46hOWpV95JGZFD3fkUPMYS"},"_contentSize":{"__type__":"cc.Size","width":120,"height":150},"_trs":{"__type__":"TypedArray","ctor":"Float64Array","array":[60,1205,0,0,0,0,1,1,1,1]}},{"__type__":"cc.Node","_name":"Img_Bg","_parent":{"__id__":1},"_active":false,"_components":[{"__type__":"cc.Sprite","node":{"__id__":2},"_materials":[{"__uuid__":"ecpdLyjvZBwrvm+cedCcQy"}],"_spriteFrame":{"__uuid__":"a2MjXRFdtLlYQ5ouAFv/+R"},"_sizeMode":0},{"__type__":"cc.Widget","node":{"__id__":2},"_alignFlags":45,"_originalWidth":2,"_originalHeight":2}],"_prefab":{"__type__":"cc.PrefabInfo","root":{"__id__":1},"asset":{"__uuid__":"55aI6lczxJ/6HqSUdQOiZL"},"fileId":"8dqNaenfhI67+ZSwxRY/B0"},"_color":{"__type__":"cc.Color","r":22,"g":22,"b":22},"_contentSize":{"__type__":"cc.Size","width":120,"height":150},"_trs":{"__type__":"TypedArray","ctor":"Float64Array","array":[0,0,0,0,0,0,1,1,1,1]}},{"__type__":"cc.Node","_name":"AdvItem","_parent":{"__id__":1},"_children":[{"__id__":4},{"__id__":5}],"_active":false,"_components":[{"__type__":"cc.Button","node":{"__id__":3},"clickEvents":[{"__type__":"cc.ClickEvent","target":{"__id__":1},"_componentId":"fbc220oTsNDQZtHkoz6kYr/","handler":"OnClick"}]}],"_prefab":{"__type__":"cc.PrefabInfo","root":{"__id__":1},"asset":{"__uuid__":"55aI6lczxJ/6HqSUdQOiZL"},"fileId":"b41l4tSnxOOplK9FXkCET6"},"_contentSize":{"__type__":"cc.Size","width":130,"height":130},"_trs":{"__type__":"TypedArray","ctor":"Float64Array","array":[0,0,0,0,0,0,1,1,1,1]}},{"__type__":"cc.Node","_name":"Img_Icon","_parent":{"__id__":3},"_components":[{"__type__":"cc.Sprite","node":{"__id__":4},"_materials":[{"__uuid__":"ecpdLyjvZBwrvm+cedCcQy"}],"_sizeMode":0},{"__type__":"cc.Widget","node":{"__id__":4},"_alignFlags":45,"_left":15,"_right":15,"_top":5.637999999999998,"_bottom":24.362000000000002,"_originalWidth":100,"_originalHeight":100}],"_prefab":{"__type__":"cc.PrefabInfo","root":{"__id__":1},"asset":{"__uuid__":"55aI6lczxJ/6HqSUdQOiZL"},"fileId":"14pshLsgdAA6UZiTJguWpA"},"_contentSize":{"__type__":"cc.Size","width":100,"height":100},"_trs":{"__type__":"TypedArray","ctor":"Float64Array","array":[0,9.362000000000002,0,0,0,0,1,1,1,1]}},{"__type__":"cc.Node","_name":"Label_Name","_parent":{"__id__":3},"_components":[{"__type__":"cc.Label","node":{"__id__":5},"_materials":[{"__uuid__":"ecpdLyjvZBwrvm+cedCcQy"}],"_useOriginalSize":false,"_fontSize":24,"_lineHeight":24,"_N$horizontalAlign":1,"_N$verticalAlign":1},{"__type__":"cc.Widget","node":{"__id__":5},"_alignFlags":4,"_left":65,"_top":113.221,"_bottom":-9.105999999999995},{"__type__":"cc.LabelOutline","node":{"__id__":5},"_color":{"__type__":"cc.Color"}}],"_prefab":{"__type__":"cc.PrefabInfo","root":{"__id__":1},"asset":{"__uuid__":"55aI6lczxJ/6HqSUdQOiZL"},"fileId":"f2pF72vA9J4qvZrMjWxb8J"},"_contentSize":{"__type__":"cc.Size","width":2,"height":32.239999999999995},"_trs":{"__type__":"TypedArray","ctor":"Float64Array","array":[0,-57.986,0,0,0,0,1,1,1,1]}},{"__type__":"cc.Node","_name":"AdvRoot","_parent":{"__id__":1},"_components":[{"__type__":"cc.Mask","node":{"__id__":6},"_materials":[{"__uuid__":"ecpdLyjvZBwrvm+cedCcQy"}]},{"__type__":"cc.Widget","node":{"__id__":6},"_alignFlags":45}],"_prefab":{"__type__":"cc.PrefabInfo","root":{"__id__":1},"asset":{"__uuid__":"55aI6lczxJ/6HqSUdQOiZL"},"fileId":"25lQu8PjBIMZcgS6cRkEao"},"_contentSize":{"__type__":"cc.Size","width":120,"height":150},"_trs":{"__type__":"TypedArray","ctor":"Float64Array","array":[0,0,0,0,0,0,1,1,1,1]}},{"__type__":"cc.Node","_name":"Btn_ShowMoreGame","_parent":{"__id__":1},"_children":[{"__id__":8}],"_components":[{"__type__":"cc.Button","node":{"__id__":7},"_normalMaterial":{"__uuid__":"ecpdLyjvZBwrvm+cedCcQy"},"clickEvents":[{"__type__":"cc.ClickEvent","target":{"__id__":1},"_componentId":"fbc220oTsNDQZtHkoz6kYr/","handler":"OnClick"}],"_N$transition":3,"transition":3,"_N$normalColor":{"__type__":"cc.Color","r":230,"g":230,"b":230},"_N$pressedColor":{"__type__":"cc.Color","r":200,"g":200,"b":200},"pressedColor":{"__type__":"cc.Color","r":200,"g":200,"b":200},"_N$disabledColor":{"__type__":"cc.Color","r":120,"g":120,"b":120,"a":200},"_N$normalSprite":{"__uuid__":"f0BIwQ8D5Ml7nTNQbh1YlS"},"_N$pressedSprite":{"__uuid__":"e97GVMl6JHh5Ml5qEDdSGa"},"pressedSprite":{"__uuid__":"e97GVMl6JHh5Ml5qEDdSGa"},"_N$hoverSprite":{"__uuid__":"f0BIwQ8D5Ml7nTNQbh1YlS"},"hoverSprite":{"__uuid__":"f0BIwQ8D5Ml7nTNQbh1YlS"},"_N$disabledSprite":{"__uuid__":"29FYIk+N1GYaeWH/q1NxQO"},"_N$target":{"__id__":8}},{"__type__":"cc.Widget","node":{"__id__":7},"_top":29.534}],"_prefab":{"__type__":"cc.PrefabInfo","root":{"__id__":1},"asset":{"__uuid__":"55aI6lczxJ/6HqSUdQOiZL"},"fileId":"c9Bb/QFf9E0b01rdOiTNs2"},"_contentSize":{"__type__":"cc.Size","width":120,"height":120},"_trs":{"__type__":"TypedArray","ctor":"Float64Array","array":[0,-15,0,0,0,0,1,1,1,1]}},{"__type__":"cc.Node","_name":"Background","_parent":{"__id__":7},"_children":[{"__id__":9}],"_components":[{"__type__":"cc.Sprite","node":{"__id__":8},"_materials":[{"__uuid__":"ecpdLyjvZBwrvm+cedCcQy"}],"_spriteFrame":{"__uuid__":"20HAQ/v/BGaZXNpKc5PXkd"},"_type":1,"_sizeMode":0},{"__type__":"cc.Widget","node":{"__id__":8},"alignMode":0,"_alignFlags":45,"_originalWidth":100,"_originalHeight":40}],"_prefab":{"__type__":"cc.PrefabInfo","root":{"__id__":1},"asset":{"__uuid__":"55aI6lczxJ/6HqSUdQOiZL"},"fileId":"90sFX+mU1PHJwVGinV/UWb"},"_color":{"__type__":"cc.Color","r":230,"g":230,"b":230},"_contentSize":{"__type__":"cc.Size","width":120,"height":120},"_trs":{"__type__":"TypedArray","ctor":"Float64Array","array":[0,0,0,0,0,0,1,1,1,1]}},{"__type__":"cc.Node","_name":"Img_MoreGame","_parent":{"__id__":8},"_components":[{"__type__":"cc.Sprite","node":{"__id__":9},"_materials":[{"__uuid__":"ecpdLyjvZBwrvm+cedCcQy"}],"_spriteFrame":{"__uuid__":"5aiJH5rfZITr7YcT1hjunq"}}],"_prefab":{"__type__":"cc.PrefabInfo","root":{"__id__":1},"asset":{"__uuid__":"55aI6lczxJ/6HqSUdQOiZL"},"fileId":"75mDhovR5GJqChAcpm4QIt"},"_contentSize":{"__type__":"cc.Size","width":91,"height":93},"_trs":{"__type__":"TypedArray","ctor":"Float64Array","array":[0,0,0,0,0,0,1,1,1,1]}}],{"__type__":"cc.SpriteFrame","content":{"name":"tgadv_label_morgame","texture":"18cd98d80","rect":[134,647,91,93],"offset":[0,0],"originalSize":[91,93],"capInsets":[0,0,0,0]}},{"__type__":"cc.SpriteFrame","content":{"name":"default_sprite_splash","texture":"02delMVqdBD70a/HSD99FK","rect":[0,0,2,2],"offset":[0,0],"originalSize":[2,2],"capInsets":[0,0,0,0]}},{"__type__":"cc.SpriteFrame","content":{"name":"default_btn_pressed","texture":"b4P/PCArtIdIH38t6mlw8Y","rect":[0,0,40,40],"offset":[0,0],"originalSize":[40,40],"capInsets":[12,12,12,12]}},{"__type__":"cc.SpriteFrame","content":{"name":"default_btn_normal","texture":"e8Ueib+qJEhL6mXAHdnwbi","rect":[0,0,40,40],"offset":[0,0],"originalSize":[40,40],"capInsets":[12,12,12,12]}}]