[{"__type__":"cc.SpriteFrame","content":{"name":"10_9","texture":"37gUv5uxtMn54+BScPx/WR","rect":[0,0,342,248],"offset":[0,0],"originalSize":[342,248],"capInsets":[0,0,0,0]}},{"__type__":"cc.SpriteFrame","content":{"name":"10_p","texture":"d4i5tiP5ZAO7R5TEhZ856O","rect":[0,0,548,272],"offset":[0,0],"originalSize":[548,272],"capInsets":[0,0,0,0]}},{"__type__":"cc.SpriteFrame","content":{"name":"10_sha","texture":"13DfvSBb5ALoks6IAaYmrS","rect":[0,0,1280,282],"offset":[0,0],"originalSize":[1280,282],"capInsets":[0,0,0,0]}},[{"__type__":"cc.Prefab","_name":"S6113Layer","data":{"__id__":1}},{"__type__":"cc.Node","_name":"S6113Layer","_children":[{"__id__":2},{"__id__":3},{"__id__":4},{"__id__":5},{"__id__":6},{"__id__":8},{"__id__":9},{"__id__":10},{"__id__":11},{"__id__":12},{"__id__":14},{"__id__":15},{"__id__":16},{"__id__":17},{"__id__":18}],"_level":1,"_components":[{"__type__":"cc.Sprite","node":{"__id__":1},"_materials":[{"__uuid__":"ecpdLyjvZBwrvm+cedCcQy"}],"_spriteFrame":{"__uuid__":"efpkhLw9FMBb3HLLIy9vdY"},"_sizeMode":0},{"__type__":"cc.Widget","node":{"__id__":1},"_alignFlags":45},{"__type__":"f8754EdtRBKOZC9yTkCq6V0","node":{"__id__":1}}],"_prefab":{"__type__":"cc.PrefabInfo","root":{"__id__":1},"asset":{"__uuid__":"3c/YMuFllM+IMJKCAgHKAJ"},"fileId":"503PhNWnZCl6ZhyK6tHY+Q"},"_contentSize":{"__type__":"cc.Size","width":1280,"height":720},"_position":{"__type__":"cc.Vec3","x":640,"y":360}},{"__type__":"cc.Node","_name":"bg","_parent":{"__id__":1},"_level":3,"_components":[{"__type__":"cc.Sprite","node":{"__id__":2},"_materials":[{"__uuid__":"ecpdLyjvZBwrvm+cedCcQy"}],"_spriteFrame":{"__uuid__":"c9+hOTsytHS5DFFeRH4rMP"}},{"__type__":"cc.Widget","node":{"__id__":2},"_alignFlags":45,"_originalWidth":1920,"_originalHeight":1080}],"_prefab":{"__type__":"cc.PrefabInfo","root":{"__id__":1},"asset":{"__uuid__":"3c/YMuFllM+IMJKCAgHKAJ"},"fileId":"01QVYUsglOs4PwCspagsNk"},"_contentSize":{"__type__":"cc.Size","width":1280,"height":720}},{"__type__":"cc.Node","_name":"10_shaBg","_parent":{"__id__":1},"_level":3,"_components":[{"__type__":"cc.Sprite","node":{"__id__":3},"_materials":[{"__uuid__":"ecpdLyjvZBwrvm+cedCcQy"}],"_spriteFrame":{"__uuid__":"e4IL0M0ipIM4HOltJjqVor"}},{"__type__":"cc.Widget","node":{"__id__":3},"_alignFlags":40,"_originalWidth":1920}],"_prefab":{"__type__":"cc.PrefabInfo","root":{"__id__":1},"asset":{"__uuid__":"3c/YMuFllM+IMJKCAgHKAJ"},"fileId":"85yyPozXNGFq+FebT4LALi"},"_contentSize":{"__type__":"cc.Size","width":1280,"height":282.66666666666663},"_position":{"__type__":"cc.Vec3","y":-346.66666666666663}},{"__type__":"cc.Node","_name":"sha","_parent":{"__id__":1},"_level":3,"_components":[{"__type__":"cc.Sprite","node":{"__id__":4},"_materials":[{"__uuid__":"ecpdLyjvZBwrvm+cedCcQy"}],"_spriteFrame":{"__uuid__":"22jt2QZjpPfpKhWaR119+M"}},{"__type__":"cc.Widget","node":{"__id__":4},"_alignFlags":44,"_originalWidth":1920}],"_prefab":{"__type__":"cc.PrefabInfo","root":{"__id__":1},"asset":{"__uuid__":"3c/YMuFllM+IMJKCAgHKAJ"},"fileId":"3ehk28XyVDio9pNpB3/6XJ"},"_contentSize":{"__type__":"cc.Size","width":1280,"height":282.66666666666663},"_position":{"__type__":"cc.Vec3","y":-218.66666666666669}},{"__type__":"cc.Node","_name":"hai","_parent":{"__id__":1},"_level":3,"_components":[{"__type__":"cc.Sprite","node":{"__id__":5},"_materials":[{"__uuid__":"ecpdLyjvZBwrvm+cedCcQy"}],"_spriteFrame":{"__uuid__":"41+jxiOrZGRq/Vw/ozahmp"},"_sizeMode":0},{"__type__":"cc.Widget","node":{"__id__":5},"_alignFlags":40,"_right":0.24,"_isAbsRight":false,"_originalWidth":1237}],"_prefab":{"__type__":"cc.PrefabInfo","root":{"__id__":1},"asset":{"__uuid__":"3c/YMuFllM+IMJKCAgHKAJ"},"fileId":"37flt8i41O1ZyQpR/nzT0m"},"_contentSize":{"__type__":"cc.Size","width":972.8,"height":168},"_position":{"__type__":"cc.Vec3","x":-153.60000000000002,"y":-162.66666666666666}},{"__type__":"cc.Node","_name":"10_1","_parent":{"__id__":1},"_children":[{"__id__":7}],"_level":3,"_components":[{"__type__":"cc.Sprite","node":{"__id__":6},"_materials":[{"__uuid__":"ecpdLyjvZBwrvm+cedCcQy"}],"_spriteFrame":{"__uuid__":"9a2IkfCWJGnIZSSeVp7uKY"}},{"__type__":"cc.Widget","node":{"__id__":6},"_alignFlags":33}],"_prefab":{"__type__":"cc.PrefabInfo","root":{"__id__":1},"asset":{"__uuid__":"3c/YMuFllM+IMJKCAgHKAJ"},"fileId":"ea40SXgAFBKrO7VqTc+79p"},"_contentSize":{"__type__":"cc.Size","width":1223.3333333333333,"height":253.33333333333331},"_position":{"__type__":"cc.Vec3","x":28.33333333333337,"y":233.33333333333334}},{"__type__":"cc.Node","_name":"10_1_1","_parent":{"__id__":6},"_level":4,"_components":[{"__type__":"cc.Sprite","node":{"__id__":7},"_materials":[{"__uuid__":"ecpdLyjvZBwrvm+cedCcQy"}],"_spriteFrame":{"__uuid__":"b1BpeRPytGK7eSbfOxnL7Y"}}],"_prefab":{"__type__":"cc.PrefabInfo","root":{"__id__":1},"asset":{"__uuid__":"3c/YMuFllM+IMJKCAgHKAJ"},"fileId":"05FKhbHQtEIruEuCW87JlH"},"_contentSize":{"__type__":"cc.Size","width":71.33333333333333,"height":29.333333333333332},"_position":{"__type__":"cc.Vec3","x":-240,"y":112.66666666666666}},{"__type__":"cc.Node","_name":"10_3","_parent":{"__id__":1},"_level":3,"_components":[{"__type__":"cc.Sprite","node":{"__id__":8},"_materials":[{"__uuid__":"ecpdLyjvZBwrvm+cedCcQy"}],"_spriteFrame":{"__uuid__":"e3iRtGORVLdJUAmYYxHKrE"},"_sizeMode":0},{"__type__":"cc.Widget","node":{"__id__":8},"_alignFlags":32,"_left":0.3355208333333333,"_right":0.2817708333333333,"_isAbsLeft":false,"_isAbsRight":false,"_originalWidth":237}],"_prefab":{"__type__":"cc.PrefabInfo","root":{"__id__":1},"asset":{"__uuid__":"3c/YMuFllM+IMJKCAgHKAJ"},"fileId":"cakhQIKOlK+p1DM4Pv8Vyf"},"_contentSize":{"__type__":"cc.Size","width":158,"height":198.66666666666666},"_position":{"__type__":"cc.Vec3","x":200.33333333333337,"y":-112}},{"__type__":"cc.Node","_name":"10_4","_parent":{"__id__":1},"_level":3,"_components":[{"__type__":"cc.Sprite","node":{"__id__":9},"_materials":[{"__uuid__":"ecpdLyjvZBwrvm+cedCcQy"}],"_spriteFrame":{"__uuid__":"9a5tQoXzlHDKtsQZpFaCf0"}},{"__type__":"cc.Widget","node":{"__id__":9},"_alignFlags":8,"_left":0.12,"_isAbsLeft":false}],"_prefab":{"__type__":"cc.PrefabInfo","root":{"__id__":1},"asset":{"__uuid__":"3c/YMuFllM+IMJKCAgHKAJ"},"fileId":"3eWXnd+09IHK+wP1b02XJJ"},"_contentSize":{"__type__":"cc.Size","width":210,"height":245.33333333333331},"_position":{"__type__":"cc.Vec3","x":-381.4,"y":-76}},{"__type__":"cc.Node","_name":"10_5","_parent":{"__id__":1},"_level":3,"_components":[{"__type__":"cc.Sprite","node":{"__id__":10},"_materials":[{"__uuid__":"ecpdLyjvZBwrvm+cedCcQy"}],"_spriteFrame":{"__uuid__":"cbf5xfQN9KmqVFCQwEujd7"}},{"__type__":"cc.Widget","node":{"__id__":10},"_alignFlags":8,"_left":0.18666666666666668,"_isAbsLeft":false}],"_prefab":{"__type__":"cc.PrefabInfo","root":{"__id__":1},"asset":{"__uuid__":"3c/YMuFllM+IMJKCAgHKAJ"},"fileId":"97H2L9qXtKcbws8hftqYLI"},"_contentSize":{"__type__":"cc.Size","width":55.33333333333333,"height":50.666666666666664},"_position":{"__type__":"cc.Vec3","x":-373.4,"y":-308.66666666666663}},{"__type__":"cc.Node","_name":"10_6","_parent":{"__id__":1},"_level":3,"_components":[{"__type__":"cc.Sprite","node":{"__id__":11},"_materials":[{"__uuid__":"ecpdLyjvZBwrvm+cedCcQy"}],"_spriteFrame":{"__uuid__":"bd99kHsuZDua/rspC0NSQQ"}},{"__type__":"cc.Widget","node":{"__id__":11},"_alignFlags":32,"_right":0.09999999999999999,"_isAbsRight":false}],"_prefab":{"__type__":"cc.PrefabInfo","root":{"__id__":1},"asset":{"__uuid__":"3c/YMuFllM+IMJKCAgHKAJ"},"fileId":"ce4SqMCftBLqo4zna7bdbW"},"_contentSize":{"__type__":"cc.Size","width":29.333333333333332,"height":26.666666666666664},"_position":{"__type__":"cc.Vec3","x":497.3333333333333,"y":-244}},{"__type__":"cc.Node","_name":"10_7","_parent":{"__id__":1},"_children":[{"__id__":13}],"_level":3,"_components":[{"__type__":"cc.Sprite","node":{"__id__":12},"_materials":[{"__uuid__":"ecpdLyjvZBwrvm+cedCcQy"}],"_spriteFrame":{"__uuid__":"7azQI8RXtN14egm9hFxDup"},"_sizeMode":0,"_isTrimmedMode":false},{"__type__":"cc.Widget","node":{"__id__":12},"_alignFlags":40,"_left":0.2503472222222222,"_right":0.27999999999999997,"_isAbsLeft":false,"_isAbsRight":false,"_originalWidth":398}],"_prefab":{"__type__":"cc.PrefabInfo","root":{"__id__":1},"asset":{"__uuid__":"3c/YMuFllM+IMJKCAgHKAJ"},"fileId":"673EuYNWVFpKbDvCeB+F6q"},"_contentSize":{"__type__":"cc.Size","width":601.1555555555556,"height":110},"_position":{"__type__":"cc.Vec3","x":-18.97777777777776,"y":-256}},{"__type__":"cc.Node","_name":"10_8","_parent":{"__id__":12},"_level":4,"_components":[{"__type__":"dragonBones.ArmatureDisplay","node":{"__id__":13},"_materials":[{"__uuid__":"ecpdLyjvZBwrvm+cedCcQy"}],"_armatureName":"armatureName","_animationName":"动画","_preCacheMode":0,"_armatureKey":"469ed45c-381e-4cc4-8c65-d77b85788c0c#1dbc6a9a-dbe5-4bed-8d07-6dc30b2e3a3f","_N$dragonAsset":{"__uuid__":"46ntRcOB5MxIxl13uFeIwM"},"_N$dragonAtlasAsset":{"__uuid__":"1dvGqa2+VL7Y0HbcMLLjo/"}}],"_prefab":{"__type__":"cc.PrefabInfo","root":{"__id__":1},"asset":{"__uuid__":"3c/YMuFllM+IMJKCAgHKAJ"},"fileId":"b7Ohvmxk9Fz6TCzgLyvEbq"},"_contentSize":{"__type__":"cc.Size","width":315.3333333333333,"height":190.66666666666666},"_position":{"__type__":"cc.Vec3","x":-13.333333333333332,"y":18.666666666666664},"_scale":{"__type__":"cc.Vec3","x":0.7,"y":0.7,"z":1}},{"__type__":"cc.Node","_name":"10_p","_parent":{"__id__":1},"_level":3,"_components":[{"__type__":"cc.Sprite","node":{"__id__":14},"_materials":[{"__uuid__":"ecpdLyjvZBwrvm+cedCcQy"}],"_spriteFrame":{"__uuid__":"21fmrlzyxJ7bM47gWBLqjn"},"_sizeMode":0},{"__type__":"cc.Widget","node":{"__id__":14},"_alignFlags":40,"_left":0.37999999999999995,"_isAbsLeft":false,"_originalWidth":822}],"_prefab":{"__type__":"cc.PrefabInfo","root":{"__id__":1},"asset":{"__uuid__":"3c/YMuFllM+IMJKCAgHKAJ"},"fileId":"dc/XJwHu9G/ZP4JklP+v75"},"_contentSize":{"__type__":"cc.Size","width":793.6000000000001,"height":272.66666666666663},"_position":{"__type__":"cc.Vec3","x":243.2,"y":-186}},{"__type__":"cc.Node","_name":"10_9","_parent":{"__id__":1},"_level":3,"_components":[{"__type__":"cc.Sprite","node":{"__id__":15},"_materials":[{"__uuid__":"ecpdLyjvZBwrvm+cedCcQy"}],"_spriteFrame":{"__uuid__":"0f1D91f/dK7pyOzudqQT6P"},"_sizeMode":0},{"__type__":"cc.Widget","node":{"__id__":15},"_alignFlags":40,"_left":0.3933333333333333,"_right":0.09333333333333334,"_isAbsLeft":false,"_isAbsRight":false,"_originalWidth":513}],"_prefab":{"__type__":"cc.PrefabInfo","root":{"__id__":1},"asset":{"__uuid__":"3c/YMuFllM+IMJKCAgHKAJ"},"fileId":"7b8pdPl4tCHZcoCXNjrrGQ"},"_contentSize":{"__type__":"cc.Size","width":657.0666666666666,"height":248.66666666666666},"_position":{"__type__":"cc.Vec3","x":191.99999999999994,"y":-142.66666666666666}},{"__type__":"cc.Node","_name":"10_2","_parent":{"__id__":1},"_level":3,"_components":[{"__type__":"cc.Sprite","node":{"__id__":16},"_materials":[{"__uuid__":"ecpdLyjvZBwrvm+cedCcQy"}],"_spriteFrame":{"__uuid__":"68Tq+FLWVHJKAZgDZ3ZPtn"}},{"__type__":"cc.Widget","node":{"__id__":16},"_alignFlags":32,"_right":0.06,"_isAbsRight":false}],"_prefab":{"__type__":"cc.PrefabInfo","root":{"__id__":1},"asset":{"__uuid__":"3c/YMuFllM+IMJKCAgHKAJ"},"fileId":"5fE189nwxNj6+IDItDSlR6"},"_contentSize":{"__type__":"cc.Size","width":65.33333333333333,"height":108.66666666666666},"_position":{"__type__":"cc.Vec3","x":530.5333333333334,"y":-180}},{"__type__":"cc.Node","_name":"robot","_parent":{"__id__":1},"_level":3,"_components":[{"__type__":"cc.Widget","node":{"__id__":17},"_left":40,"_bottom":16.666666666666664},{"__type__":"dragonBones.ArmatureDisplay","node":{"__id__":17},"_materials":[{"__uuid__":"ecpdLyjvZBwrvm+cedCcQy"}],"_armatureName":"body","_animationName":"changtai","_preCacheMode":0,"_armatureKey":"31114672-0753-4171-8055-f3bbadbd4e6b#f889c817-505a-4aef-be35-96da1f9ffd56","_N$dragonAsset":{"__uuid__":"31EUZyB1NBcYBV87utvU5r"},"_N$dragonAtlasAsset":{"__uuid__":"f8icgXUFpK7741ltofn/1W"}}],"_prefab":{"__type__":"cc.PrefabInfo","root":{"__id__":1},"asset":{"__uuid__":"3c/YMuFllM+IMJKCAgHKAJ"},"fileId":"2d7TZcv8RJd7IBtK+kKU9s"},"_contentSize":{"__type__":"cc.Size","width":344.0333333333333,"height":291.3666666666667},"_position":{"__type__":"cc.Vec3","x":-419.116,"y":-223.701},"_scale":{"__type__":"cc.Vec3","x":0.6,"y":0.6,"z":1}},{"__type__":"cc.Node","_name":"bdNode","_parent":{"__id__":1},"_level":3,"_components":[{"__type__":"dragonBones.ArmatureDisplay","node":{"__id__":18},"_materials":[{"__uuid__":"ecpdLyjvZBwrvm+cedCcQy"}],"_armatureName":"boy","_preCacheMode":0,"_armatureKey":"97066607-fc1e-46b9-a895-de268158aa03#9081055a-ef62-4388-94ed-ff049015c5f5","_N$dragonAsset":{"__uuid__":"97BmYH/B5GuaiV3iaBWKoD"},"_N$dragonAtlasAsset":{"__uuid__":"90gQVa72JDiJTt/wSQFcX1"}}],"_prefab":{"__type__":"cc.PrefabInfo","root":{"__id__":1},"asset":{"__uuid__":"3c/YMuFllM+IMJKCAgHKAJ"},"fileId":"18h2fNfIVNvYf21wN6Y/LX"},"_contentSize":{"__type__":"cc.Size","width":296,"height":462.4466666666666},"_position":{"__type__":"cc.Vec3","x":-209.166,"y":-170.665},"_scale":{"__type__":"cc.Vec3","x":0.55,"y":0.55,"z":1}}],{"__type__":"cc.SpriteFrame","content":{"name":"10_01","texture":"9f1kdZP2ZCTosq7dYVDmpk","rect":[0,0,824,168],"offset":[0,0],"originalSize":[824,168],"capInsets":[0,0,0,0]}},{"__type__":"cc.SpriteFrame","content":{"name":"10_2","texture":"08pn9qYBJPwLt5gdJFl9ih","rect":[0,0,65,108],"offset":[0,0],"originalSize":[65,108],"capInsets":[0,0,0,0]}},{"__type__":"cc.SpriteFrame","content":{"name":"10_7","texture":"a6a9vpBHFNFopVsrkwo2ua","rect":[0,0,265,110],"offset":[0,0],"originalSize":[265,110],"capInsets":[0,0,0,0]}},{"__type__":"cc.SpriteFrame","content":{"name":"10_1","texture":"15HHjEcvpMxKqNyH7GAIki","rect":[0,0,1223,253],"offset":[0,0],"originalSize":[1223,253],"capInsets":[0,0,0,0]}},{"__type__":"cc.SpriteFrame","content":{"name":"10_4","texture":"9fB/1PvDlLO70dikGbxIzv","rect":[0,0,210,245],"offset":[0,0],"originalSize":[210,245],"capInsets":[0,0,0,0]}},{"__type__":"cc.SpriteFrame","content":{"name":"10_1_1","texture":"3cuG1bqKBGFbBt3k46lXbp","rect":[0,0,71,29],"offset":[0,0],"originalSize":[71,29],"capInsets":[0,0,0,0]}},{"__type__":"cc.SpriteFrame","content":{"name":"10_6","texture":"e55KKBWfJDdZ9klVCpsrJg","rect":[0,0,29,26],"offset":[0,0],"originalSize":[29,26],"capInsets":[0,0,0,0]}},{"__type__":"cc.SpriteFrame","content":{"name":"10_0","texture":"b6j9dQVYlHoLmlQQb/Znf5","rect":[0,0,1280,720],"offset":[0,0],"originalSize":[1280,720],"capInsets":[0,0,0,0]}},{"__type__":"cc.SpriteFrame","content":{"name":"10_5","texture":"49Uwyno99LqLA9zQBgcYi2","rect":[0,0,55,50],"offset":[0,0],"originalSize":[55,50],"capInsets":[0,0,0,0]}},{"__type__":"cc.SpriteFrame","content":{"name":"10_3","texture":"8cWbPPY+xNBYCV/Letksxp","rect":[0,0,158,198],"offset":[0,0],"originalSize":[158,198],"capInsets":[0,0,0,0]}},{"__type__":"cc.SpriteFrame","content":{"name":"10_shaBg","texture":"0bGBM/wOJIlLy47kyoD2GF","rect":[0,0,1280,282],"offset":[0,0],"originalSize":[1280,282],"capInsets":[0,0,0,0]}},{"__type__":"cc.SpriteFrame","content":{"name":"10","texture":"44OzmPOK1HlZ94u/n1rCDC","rect":[0,0,1280,652],"offset":[0,0],"originalSize":[1280,652],"capInsets":[0,0,0,0]}}]