{"paths":{"0":["sprite/games/gbz_screw2",3],"1":["sprite/games/gbz_box4",3],"2":["sprite/games/gbz_box7",3],"3":["audio/skill_clear",0],"4":["sprite/games/gbz_screw7",3],"5":["audio/game_bgm",0],"6":["sprite/games/gbz_box0",3],"7":["sprite/games/gbz_box3",3],"8":["audio/skill_unlock",0],"9":["audio/screw_out",0],"10":["audio/skill_remove",0],"11":["sprite/games/gbz_skill3",3],"12":["sprite/games/gbz_box5",3],"13":["sprite/games/gbz_screw6",3],"14":["sprite/games/gbz_box6",3],"15":["sprite/games/gbz_screw1",3],"16":["sprite/games/gbz_box1",3],"17":["sprite/games/gbz_skill2",3],"18":["audio/game_lose",0],"19":["sprite/games/gbz_skill1",3],"20":["audio/screw_empty",0],"21":["sprite/games/gbz_screw4",3],"22":["audio/game_timer",0],"23":["sprite/games/gbz_screw_core",3],"24":["audio/game_win",0],"25":["sprite/games/gbz_screw5",3],"26":["sprite/games/gbz_screw3",3],"27":["audio/game_click",0],"28":["sprite/games/gbz_box2",3],"29":["audio/screw_in",0],"30":["prefab/games/GbzLevel13",2],"31":["prefab/games/GbzLevel27",2],"32":["sprite/games/gbz_box6",4,1],"33":["sprite/games/gbz_box4",4,1],"34":["sprite/games/gbz_screw6",4,1],"35":["prefab/games/GbzBoard7",2],"37":["prefab/games/GbzBoard2",2],"38":["prefab/games/GbzLevel18",2],"40":["json/gbz_level12",1],"41":["prefab/games/GbzBoard5",2],"42":["prefab/games/GbzLevel11",2],"43":["json/gbz_level20",1],"44":["json/gbz_level10",1],"45":["prefab/games/GbzLevel29",2],"46":["prefab/games/GbzLevel25",2],"47":["prefab/games/GbzBoard6",2],"48":["json/gbz_level26",1],"49":["prefab/games/GbzBoard17",2],"50":["sprite/games/gbz_box7",4,1],"51":["prefab/games/GbzLevel28",2],"52":["sprite/games/gbz_box2",4,1],"54":["prefab/games/GbzBoard10",2],"55":["json/gbz_level21",1],"56":["sprite/games/gbz_screw7",4,1],"57":["sprite/games/gbz_skill3",4,1],"59":["prefab/games/GbzBoard9",2],"60":["json/gbz_level6",1],"61":["prefab/games/GbzLevel10",2],"62":["json/gbz_level27",1],"63":["prefab/games/GbzLevel5",2],"64":["json/gbz_level28",1],"65":["sprite/games/gbz_screw4",4,1],"66":["sprite/games/gbz_box1",4,1],"68":["prefab/games/GbzBoard4",2],"69":["prefab/games/GbzBoard31",2],"70":["json/gbz_level3",1],"72":["prefab/games/GbzBoard51",2],"73":["prefab/games/GbzLevel19",2],"74":["prefab/ui/GbzExitLayer",2],"75":["prefab/games/GbzLevel12",2],"76":["prefab/ui/GbzLoseFullLayer",2],"77":["json/gbz_level17",1],"78":["prefab/ui/GbzTipLayer",2],"81":["prefab/games/GbzLevel4",2],"82":["prefab/games/GbzLevel2",2],"83":["json/gbz_level5",1],"84":["sprite/games/gbz_screw3",4,1],"85":["prefab/ui/GbzMainLayer",2],"86":["prefab/games/GbzBoard14",2],"87":["json/gbz_level22",1],"88":["json/gbz_level19",1],"89":["prefab/games/GbzTarget",2],"90":["prefab/ui/GbzWinLayer",2],"92":["prefab/games/GbzLevel23",2],"93":["prefab/games/GbzScrew",2],"94":["sprite/games/gbz_screw5",4,1],"95":["prefab/games/GbzBoard48",2],"96":["prefab/games/GbzBoard11",2],"97":["prefab/games/GbzBoard1",2],"98":["prefab/games/GbzLevel0",2],"99":["prefab/games/GbzLevel8",2],"100":["prefab/games/GbzBoard12",2],"101":["json/gbz_level30",1],"102":["json/gbz_level7",1],"103":["prefab/ui/GbzSettingLayer",2],"104":["prefab/games/GbzLevel20",2],"105":["sprite/games/gbz_box3",4,1],"106":["json/gbz_level25",1],"107":["json/gbz_level9",1],"108":["sprite/games/gbz_skill2",4,1],"109":["prefab/ui/GbzLoseTimeLayer",2],"110":["prefab/games/GbzLevel6",2],"112":["json/gbz_level8",1],"113":["json/gbz_level13",1],"114":["json/gbz_level16",1],"115":["sprite/games/gbz_box0",4,1],"116":["json/gbz_level1",1],"117":["prefab/games/GbzLevel7",2],"118":["json/gbz_level11",1],"119":["prefab/games/GbzLevel24",2],"120":["json/gbz_level2",1],"122":["json/gbz_level4",1],"123":["prefab/games/GbzLevel9",2],"124":["prefab/games/GbzBoard15",2],"125":["prefab/ui/GbzMenuLayer",2],"127":["prefab/games/GbzLevel30",2],"128":["sprite/games/gbz_screw_core",4,1],"129":["prefab/games/GbzLevel26",2],"130":["json/gbz_level23",1],"131":["prefab/games/GbzBoard8",2],"133":["json/gbz_level14",1],"134":["json/gbz_level18",1],"135":["sprite/games/gbz_box5",4,1],"137":["prefab/games/GbzBoard41",2],"138":["prefab/games/GbzBoard3",2],"139":["json/gbz_level29",1],"140":["sprite/games/gbz_screw1",4,1],"141":["json/gbz_level15",1],"143":["prefab/games/GbzLevel17",2],"144":["prefab/games/GbzLevel16",2],"145":["prefab/games/GbzLevel3",2],"146":["prefab/games/GbzBoard16",2],"147":["prefab/games/GbzLevel15",2],"148":["prefab/games/GbzLevel1",2],"151":["prefab/games/GbzBoard33",2],"152":["prefab/games/GbzLevel14",2],"153":["sprite/games/gbz_screw2",4,1],"154":["prefab/games/GbzLevel21",2],"155":["json/gbz_level24",1],"156":["sprite/games/gbz_skill1",4,1],"157":["prefab/games/GbzBoardItem",2],"158":["prefab/games/GbzLevel22",2],"159":["prefab/games/GbzBoard13",2],"160":["prefab/ui/GbzRankLayer",2],"161":["prefab/games/GbzScrewMove",2]},"types":["cc.AudioClip","cc.JsonAsset","cc.Prefab","cc.Texture2D","cc.SpriteFrame"],"uuids":["0cRXuYZgFLQ7mmBzohy1vr","160iFOjhlPiLze0BcA/paC","2113vlV6tJPql7za9IrR/M","28415c93--184-1-49-44-9-f67-b0fb1e3d06be","2bvuSFDwZJkLiJZhNmPq/z","492WnXFW1EGrxr9ui4TWWT","57Qd+Y0W1A0JYbXRWhNIO3","590gAMdRxPx4hIjd/MR2qp","5efbb2b3--7c8-c-46-95-b-734-df897ea4e458","65hQwCAxtHhr74X+0y693H","6emKgQrplKFqME9wDa9C/b","78EdRGAxtDebkspyDeEoVi","88zCA3TjRK2pQOvH2bVZir","8ef0JNRzVMIICjQLFAn/Bh","8ezxahVIdNoJVMO9n1FwtY","992hOYy69AcrPqxmnmw/0F","9bzYiB8PxFzbGgMNAIaGVi","9eWW04fzlMuIkdWjaDOq1v","a855fa43--043-5-4b-f7-b-e4c-463bb5361c83","b2tsEPUZdLD707llG3P1bY","b9307d6c--f16-3-4b-01-8-f92-267e3e0a313b","bcALZSoNNMX4O/rY0K2CkQ","c097232b--341-9-49-a4-b-f8e-9e9d0cd7f349","c4e259e5--a64-e-41-65-b-449-6e13b1a2eba8","dc383ae5--e13-7-46-5b-b-510-d2888993d6b4","e1mJ1Y6E5I/7o2TrPnPbIH","e4lYDPfF5FW64MUm1ZXjWs","e55427cf--012-d-47-bc-9-229-20eb22a981b9","eaH2Jjz4VGEo0hHH/kfizB","fd3f30b4--69a-a-40-bb-8-560-5939be8dfed1","01WBpcqtlCLYu2fERZi2zN","01sqNTvOBIRoXqpzBAfY7q","02KG6u6g5K/5ekXqthG2uU","02c8b0n6RNZq1ynkDaL319","02il93jIdIPZ/jjV8Dgy5Y","044aH2vuJGNbDR0tvVkdw9","0518c8d8--bbc-b-47-c8-b-658-7b80903934ed","06khcIUUtDF4orZtxuUx6m","09H7pOAcRC+qJchRHYCvL1","0bb91ea3--82d-3-48-b4-a-bcb-6b95bcd16fbf","0eMuedI71LXrFpeZhNlA8V","13nSj1n7VLQotGSwOYD9bo","156Qxtf8VOupcSIP91yycY","19irfX4f1Ap4gLtZWbdeMz","1b36I/0+VKHJ9Ur5A438g5","1crbhIx5RFoab2ym2OrJzy","1edXsnchtFG74c9UngVMtI","1eiwMCMANFW4YGAg/1H4WQ","1ftn22KmlIcI2E5nKn+5Nv","23i1MrIu1DK4Eki0Mmco9E","25UtTUR8JA5IdNCmuvq+Me","26Qn4pYe1JXphxAerof4PI","27MJ+CMVpCHILBPADkiHB9","278cb93c--4d6-7-47-b7-9-b98-e6a6c6cad994","27t0DVrJJJh7r8CWx2vGzf","2bN7QroGpOVJclArxkFUmF","2cTBBLthtJLa3PNc4mkvLB","2dSpnOi7FL+pbMIUv1aSV7","32a45a1c--611-1-44-c3-9-427-c2b3d0a9c7f8","34vcl9t/VD8qBo+2qgYZBt","37cM8PHghBKLH0xvMVs8q9","372SGSItlJXoBF/7HOJTh7","39mGeFXa5GAbMSkkWcmH89","3aNC5uhiBDWJa7u1uc++pu","4052dz2MtJwoECiGCMqB7r","41eSCVnmZGFZigKVufopi+","43WOdCog9G+q915/EQeMKr","455c1679--064-9-49-ef-b-359-09e770087379","453EL7a0VHPK+FI9p+yjxf","46EgQDx+JE1YWisyDmI0lw","47KJJfcdVMRZYdtyV9rC/i","473b44cf--5e8-e-4d-7b-b-f7a-4251f1619660","49qwztcntIo7SjSPnBNQyu","4aEHTF6EZIho05gA6p5VZJ","4b473394--81e-d-4f-a1-a-649-931288e1a295","4bf22FTw9Gl5HlmEMY19Fw","4c3U7NQbNGDY8ZGhw4PGMc","50V4oVNLlBMb8XHqEmIqkg","51e51961--8eb-f-4a-ce-a-6da-402358b29437","530f4cd8--cf8-f-40-55-a-709-42fcf870e404","557220d1--b5c-6-40-90-a-d2c-e134c89e64d5","5875xUZ/JBH7HmwvgCoe9T","5a45w7ePtGOY5eitJmScrG","5bshMHrwBLPbW58FLwd0or","5drDc412VPM40cpcshfrxX","5f0bd966--180-f-43-c2-8-76a-a3de7a5b7340","5f7pfu9dlNzrm8ZxS68dYh","60HIg3nWpPvo9iwGNJfS+5","60gIbgn5RMJphICfc+PsHg","643EMiC2NO06a5L1j6Mbyd","6a6a09aa--eb2-4-41-2c-a-9d4-bbf314f67a12","6bc67f6a--682-3-4b-c4-8-9de-aebbc63ed47e","6eq/yHZA9FYKP8aUAu9Czj","70HDT1YvNBLZHGvw6E6aJC","73SQgdf2xKqLQ/mqiw+ZvE","747PGRUZZFYKDF1FR5P4XS","792MRVK6RAqrz8Vm1lb0kK","7fLupfxopEEL/1J29Fvsfi","80CNbo8wZO7rnFy5iqiEa6","85ftw0z7dAGoFxlIrO5gaI","8bXNj5EHNAQ6c754Z7q8sO","91G2gA56xFl7sK12rc5x7c","92AComvDNFgYL3LuK6nyEP","949acee1--0e2-8-49-42-b-123-f403805d1cc8","96XWmD6zhFZpRArVCwyKEQ","98RcGWcqNLUJQtlo6FB5Qh","99vS4cCzFG0JvNHsJPg4cl","9cVLN3gfxF1ZSZA6tcBBlE","9d26ttj1dMJolCAElkL7uN","9fvB8buEpBBZSTUq5A6zlZ","a3AAg5vOhNjpL7+RfYwdrz","a842972d--f9e-1-43-d1-8-652-5e131736f501","aazbITLFFF7JsTyEWmfbZK","b0ys2JyWdMRYRrZ/xrdH5L","b3Kd7DcJ1BtabMx674wU/g","b3tAAy5+pJa5KeWG493x5c","b4nGK1U69IzJM5DX+2gzao","b5PtWZ3adBioSzFGZt0acO","b5RnXY92RN2InpLgdF8bd2","b8wbYrp4FIlK5YUhl/NWR4","ba4IpNz9VPlrMgqmfKZXiD","bb700340--019-d-49-ac-9-326-08c300f9c1fd","bbo/jVqihPLaGgjkxQdtyA","bffFaaEIRANJZIBPk+/7gF","bf+SGoYS1FPZWC5YQei2t4","c01a2bca--2b9-7-4c-a5-a-bec-c5b5b2fb9764","c1iATBVEZKn7lpkq+bxNIl","c3EwuGwqFM8rMKbm5x96ds","c4eba435--c0a-e-44-be-8-f89-21cfdf4e5ced","c6RYWnMJlKvpymVjD63nVy","c7MUIA0FBK/baIOM1Wd30L","c9WpuNzkxEX7P1oDa3tapr","c9ebd9c7--0d3-e-40-95-8-9a8-fda4e9d76068","caaEJTjm1OoYm0e1RiVl1W","ca4+mEGYJGLICjnP8QONcH","ccCHb+VCpH/4sF4XiNlB/9","cc700d10--8cf-6-47-f9-a-232-ccd71bc1379d","cexL6HEQJEI4/f86Jn1sFR","d1h5JUKWNG/qoq1eOO3NBT","d6BdTlQsFCT4gi/VK4p29G","d6HbmDaB9P04s4R3bIZ4Pm","d7FHUmg5BJJ5UKr6hQGzPz","d9AX5+jitJ/Jzs5kks573x","e1+t13WC9PtIY2CuJb5Amu","e5kqw7liNFnoZsQuvelq0h","e63U3UaD5BV5n9KO8/auw5","e7AnENADhEoqnxvsw0nJWg","e77cdgYLlD34mygo0Lamge","eaQ7+6nQhH0rjjcchcSoqG","eb27a3c4--ea0-6-44-1e-b-850-36359b83ec45","ecar909rpNEYbU8Wlis5l/","eeqx/c22pHqaXoodXIYK2Q","f0oVVVhGxPkazIlxlyIXhL","f0rgjzRPpCcIxYTN9Qoypb","f03i9rklpFuKGWzaXaF2L0","f3eQOF0EtBP55tCP4Yk5di","f6bFo2lShGDLFGztQidYgm","f7KGt9ksNHj6hBokz/cWxp","f8ezyAh59CpawJ/knieZc1","f94ddKl6BAeqeray7ogalj","fa789d08--eba-d-4d-4c-8-e42-f97491d0bf4f","fdXd/BJZdDy5ozM+YfIMH9","027287f2--533-0-49-96-b-9ff-59b403ee0aaf","02delMVqdBD70a/HSD99FK","035deee6--09d-2-44-fa-a-7a5-8efdc142a040","08EB0w+75FAam0EqioYVKC","15BpD2gTlB05OKZSgxmauO","156d4cb9--188-6-4a-71-8-69a-4fcd7f86215a","22a73de2--176-d-4d-f5-a-e17-66e013dd87f1","27gnjHov9FHZHiALVOenn+","27orV151JEFJZQqlWsY7HQ","2981b02d--394-3-46-07-a-70b-68316e40279c","2e09426b--c78-c-40-6e-9-278-748081aaaced","36gl55ugFGDIdy6vSlF9mC","40X4wj6upMuYu0K9edvtgz","45cd8867--e40-5-4f-b3-9-932-981b6fea510b","47FjtcvYhCLK46fxvMwL/V","56fB8PbE1Ik5ub+YcmfE8o","5cesL8AFFPB6iPzQoeYRMU","5c0ymwJ2dKnL77hxvxGavL","5e/gpl4LFNGoTU9CvaI/SY","63g7ZmNc9GD5nhhi8rDNYP","6d1Rr5oP1FXrj6VjoZP6Oe","702T8cXdhP8ImBt3zyaoFl","75bb2a47--850-c-4b-9c-b-876-ceb4f057e7b7","79Mr2HFs1ES55c1X76dHw3","8141693b--34a-d-4e-c5-8-fd0-db67ffd6546a","83slYWPV5B74wq8E/WQ06E","8aQNyXbsNNiYq6rdbA2KtM","a2MjXRFdtLlYQ5ouAFv/+R","a7996c17--f7b-0-4b-4a-8-fad-bfbe6d01f449","a9byDrDWNKWaeOXZjWHBuN","b952MBJ1FIQ4RcXipdzpOG","bab89571--b41-3-41-97-9-aa1-fdf5d539f92e","c1KI4PVh5CNbUpyfOTPxZE","cc0ede00--b67-f-44-44-b-685-409f681fb553","cf9ruJfjtOF6qmlYBk5pI1","d04161f0--d0b-4-41-51-b-b08-aac225fcebad","dbMMV1TfBFpolnPnUTRs+K","ddae121a--5e4-5-42-4b-b-2c5-9825a13324e5","e6xzHwZkhJyJs3Gsx5u9rD","ecpdLyjvZBwrvm+cedCcQy","ec/cxa1ApI3bUgdZ+4uQNt","f129fac1--e6d-8-44-0f-b-3a2-2e03af14cc03"],"scenes":{},"redirect":[163,0,201,0],"deps":["internal"],"packs":{"0445cfd53":[179,159],"0463b84c7":[167,189],"0522c3d8b":[103,190,195,199,203],"055a104b2":[66,115],"060a8f7c0":[181,124],"073002898":[57,78,108,156],"084544b20":[162,186,193,125,197],"08eb40aa4":[168,171,85],"090b0fbf5":[86,182],"0911911f4":[49,188],"0b2c89373":[36,39,0,1,2,53,4,58,67,71,79,80,6,7,91,11,12,13,14,15,16,17,111,19,121,21,126,23,132,136,142,25,26,28,149,150],"0e3de5561":[191,128]},"name":"resources","importBase":"import","nativeBase":"native","debug":false,"isZip":false,"encrypted":false,"versions":{"import":[30,"3af5f",31,"8b33a",32,"4c41d",33,"9bfe0",34,"4bf00",164,"81a61","0445cfd53","26625","0463b84c7","3d2b7",35,"b6687","0522c3d8b","30c54","055a104b2","d5bdf","060a8f7c0","c595c",37,"5aaea","073002898","72a09",165,"1a24c","084544b20","32dfd","08eb40aa4","0ddf8","090b0fbf5","838f2","0911911f4","80bca",38,"98634","0b2c89373","9a846",40,"abbfc","0e3de5561","c7411",41,"60440",166,"deb60",42,"7b6af",43,"54cb8",44,"7bee5",45,"337c6",46,"a4e6a",47,"83f2d",48,"5bb1a",50,"9497a",51,"78b18",52,"949fc",169,"38dff",170,"70e4f",54,"fb30d",3,"a988a",55,"44a96",56,"51114",172,"ae4a0",59,"dfcee",173,"8ce8a",60,"9af02",61,"a6aa2",62,"ab65e",63,"93433",174,"ebf76",64,"791fb",65,"f34dc",175,"fa4be",68,"573bf",69,"9c340",176,"b82ed",70,"affd3",72,"b6143",5,"8e883",73,"459ea",74,"9e56a",75,"67084",76,"88dcc",77,"67f4a",177,"a0d30",81,"959ab",82,"99caf",83,"a3c65",178,"0b3c2",84,"37f12",8,"65404",180,"a9847",87,"bcc79",88,"8aedb",89,"16479",9,"a3571",90,"c7ba7",10,"e5409",92,"90510",93,"4a49f",183,"c2a8d",94,"5df30",95,"dcdc8",184,"25ba9",185,"6aaaa",96,"fc493",97,"70941",98,"58455",187,"6ad83",99,"75ce7",100,"971a0",101,"da289",102,"c382c",104,"fc98f",105,"c21ee",106,"27fc5",107,"d8a8f",109,"1414c",110,"d6125",18,"18c5d",112,"d2d00",113,"8c174",114,"05dc2",116,"6a59e",117,"13f66",118,"58dd6",119,"2a058",20,"4e632",192,"47f89",120,"ecd4e",122,"64633",123,"c07cc",22,"539ce",194,"4ee87",127,"9e948",129,"8e0f0",130,"b097a",131,"aaea8",133,"0ecb9",134,"a63b8",135,"89df6",137,"8d343",196,"9f82f",138,"1b722",139,"bfc0b",140,"4e477",141,"f20b2",198,"09c43",24,"c2efa",143,"1a6e9",27,"dd254",144,"90b46",200,"acd73",145,"b5f0b",146,"85177",147,"c0a0c",148,"4c765",202,"1dd9f",151,"fa5c3",152,"0c109",153,"9615e",154,"4134c",155,"c71f1",157,"a3031",158,"39e72",160,"330ff",29,"6e127",161,"ce2fe"],"native":[36,"628b7",39,"3f7dd",0,"ff90d",1,"c6fb8",2,"af2cf",53,"fbc10",3,"c2479",4,"7bdd9",58,"208c7",67,"ba60c",71,"1ea42",5,"6ff45",79,"2c2d2",80,"c592c",6,"477f7",7,"a5d5f",8,"9f24c",9,"16cd9",91,"f623d",10,"35968",11,"c5e79",12,"633ee",13,"f9ce8",14,"814d6",15,"c95ad",16,"f4cb2",17,"98de2",111,"51db0",18,"1853b",19,"924fe",20,"3279e",121,"ed226",21,"bcddd",22,"ec550",126,"443d9",23,"09951",132,"ad7c5",136,"d2748",142,"90e26",24,"6a043",25,"e5682",26,"545c2",27,"1be98",28,"a48f2",149,"32a3e",150,"1063a",29,"49556"]}}