{"importBase":"import","nativeBase":"native","name":"bullet","deps":["monster","weapon"],"uuids":["10TF2TTbJJdZkK0LQeIiFd","111mvw1RVHTptGCQr06HYO","255oWl5dtNv76+gb1xSGHd","371wq4W91NaasPLBjWegmN","4dF1l7ykVGN4xkl+0lojra","68tz4D7RNPCK86fqntizY7","6aWkNU9/FE9YQBaT7bmObz","7cTZjmhkdGmZ6Mfm5fcVW8","98+6k1jAhAWpXnecWRLr0c","9b6yIvaqxEsawvVCCA2t1K","bfQReDYzxO07JIWlkBHE4S","c95iJPXMZO04UVZIdTt506","d2D2q/gqBPV5cnccOjNBM4","ddIewH5SZEKK9lokmRBxow","ddehFqcWND/arB71DhrDct","e0FrN6NuZIgYPLdfIZTewQ","falfRNBgdEBbnQ0x3/S4lw","018PRUTt9Cj5GLJMO/h54Z","024DRvI19J8aTmIdRBqBeY","04VAc0xpJJ1ptKvFLRooAg","049he3591OkJgCznlaslxz","07AFMsZKVO37+/sXmEesg9","07B8IYmc5P4L4XmAMGtTbY","08pAzbdhxHEKiAP7tYQRy8","0bQBfQ1npAwJrp+DMJblc9","0bkSmo+2BDrKkRfzAHutK6","0bp7ce0W1FV6PsDACZCaw6","0b4UWB5z9Jy4rL+5tDXhAe","0caVm/t9tJxLycYULRc4j/","0ccjOxu51MOLXxFj7agF+y","0ddnlLBHNEx6j3nUroJBHF","0f8OLmrctPoqKtXoEC2k/D","10bw9G5vtPUoVgrUaSJnze","10mMiT4wJNGpqeLMnQIkv5","10na3T2OdOuKtq2tNrx3ag","11zZBubK5HOpqXDgioSJpF","11zqbnn5RHiraB0y7iUvm1","12qxxQUj5Ft7ZJUsI3iheF","14B4p4JYBASb7KANH1NuFC","14Q/JdlY9Km6cL7JOCbxCz","15dJrwvTBBs7iYZWxUQIHJ","16jYjGPlJDub5mnn5dFbeL","16p8T2NLVJI6KjT7eD2oAn","17Pvml1PZEEZAn/41xZvCv","17tVFptNpKVJaEcxBNvoLs","19zvPzNwZKOI0Q3E30t25M","194inRvHND27/kFubYzrkR","1cf/Ig+RtPSLhqSqPNsf4d","1eIRkygrZB/pUZEi9JEiAI","1eI4tuFZRBda+gJ+xHzrwL","1ejlzSg9ZHWrifJwPM3MsB","1f7g+PENZKuqLAZCseywD2","24Bm/rFkxNzKf0p0/i/Grt","25O/2t6FpK3rKoSiRKh3jm","255ucEIe1ED7Gj1Q42VhcJ","28rtTLiGRLFaw4QcwGTxul","280EX6hnBEGocuv41VC5HF","2dTn38B3pPvL/PS/fMiuAl","31Hl7Sz5dGAKItqiC1wxjH","346TkYcXFLtLJDPf67BcId","38ELtNc1VHaZqwU/Hb8nNg","39/JRkDiNJ17DCbSin3049","3awOIGMN1FkYmqLM1jC8ny","3bs42tOTlA4IOP0OcdnNOL","3e5c9HGHFIm5jsNkyH2e26","3fq3LDyfhLXb+cGFN0hMVL","40O90SEYRF8JaE/FzR541O","42/VZgJvZIc7CIygR0vztV","44ZxDN/exLA4h9ON6JKrBJ","462j9KSPVLI6jxRbrw3bs3","47MVa1p8hLj6xOvh8LuvWs","47M3zqnvFEooE2CxRe1xSq","48Bl2iEY1Np7OHnwei+dab","4dueRlyPtD3Lk2ZSnwWqER","51H0dO4PJJzrwUyrRVCTjh","51tB9onJ1IMrPSCLHXnMyL","520hOj+DpInIEUHayOipXY","53S/5wX09MpoOwCU1uQSMc","54T08/inRLTZxe023t8TNH","55MboFgfJKyLJrE6op1KCI","56msVAtitBvIoNaNpUn1km","58mOlm+9lGRKAKj27T9o/w","59ufF1/IlOwpOY2ue0jPn4","5aO2kbLn9EoqJvOe/yPENg","5cFshZQv1Ju7pJYa4mZi0Q","60h/AID3hA9Z0391NMV7vx","61h9DkRUJDy75bzM0QMw1l","65NUN7CjVDH61dR86l7cEJ","67NNEMsf5O5oYs+4B76VBJ","6aCm73DIpIwY2ky5m8MXxX","6aCtQZ+ZZEyaERSGoxiAY4","6bYiI0JipBfaM73qjDhBso","6cF7vHaA5K1p7NrN1jW7uf","6cGnj12DdClYXjYjR9xqtL","6cbHfQ7nNOyZc0KRmQwo2S","6dwfF3BBNAxqdxN/qnRUPX","6frla4ojBHJaq8yzrNJJv5","72cye7QKdM6JWuvwdRp0QB","72/cyFkB5PPYAfyCmhh//g","74rxQzEj9N+65F9TNNsFh7","76gtMW8KFGFandI6Ka7IUb","78SshxEKFJwrmoi3KSjpNB","79Vgb5vB1FrriLBLEyhG3v","79+6VKJA5Mj6XWYoCH/8Uv","7aLXXpJyhLE670xxjfBsZO","7a3CK+g5ZDiYt1Zd3iZyl1","7dBfRtKrlMW7ioRdeMIoBo","7fHAPD9d9Kj41JfsX/UakR","7fmABzGYpNSa/mvYi3mKl+","82mGVC91FPY5FhTb3UjA4l","83TjcpWBVOZJRtPvLKjK8I","84eaR3c4ROg5QH+Xt5M2U5","84y6nFTMhPOpXnfP35YyOS","85hlrtFApErpxAbGGyu1Jb","88SAD1+BRDrr3+zRWrvbbV","883ZpDP2BFtJxcCpAYESg5","893Q/s8q1K652gsq9HM7MK","8a+W+AwrxOs7Db48nHZCOt","8cgKoOwHpHva7HhgICBxPT","8c1/QX/FJIDIwNvppKCAMz","8dZA18k81DEKwFJpmtZpr/","8dzTMeep9G3bYnFjHK2RHK","8eGl04E2lPz7xU0vbm4Nlx","90nLLZpYVNAZew6+lgGkeZ","91HFE+kURCm7JwtU8egfLi","91QF9RqGxEToWdfIHa7Mvp","92V9AQ2YdHMIhvhb4JTxrV","93oaxDDO5BBow6Tv0VO43i","94C817p2VFq6Cc81r4q6AE","94OK3+SKxM6rdMfNdzUmXD","9461nUfTJOuIAOBG8g6uTv","95KzJV0DlJHYtuT/qKbCo9","95vyTslLpBI5tQMANcZ8yP","96X6we/y5NNadHRN+B2xFs","97MRXpX+VJBL0IBUVm+F7w","98n+XY4UNI86aIQuFYO+O5","9aOfe/3TBCJqc8EDa6lCTm","9aSFoxUg1LD5wgAYNPLnt4","9bi8YAlu5C+KSA69ZHvDHA","9ccAJVTzBCvpuImKuC4/3N","9e4SsZx9RHBadChj/gdGfv","a0TlVSOehEYpuMaLuqATHy","a3NZpbovZMX455Qa2cC9pa","a6Lb+LXMNDqaLzEb8lkQfu","a6RA8rtgtO06TayYpLJmBs","a61pM9ihtFXL2rHsHUmAFe","a922Mt06hIL6cJRj6n8nhd","abMztMnytBm47ah3blt0sV","abcdoDpHBKs7IRjXUk2Ova","acA5QZdh1F37QH7cSXMFph","acqB11cnBKt5tClcvHKAAH","afZTjzH7ZLc4uYcAcuYMBq","b0ms/x8ltBxLB7/1Y9enwY","b2QNILH6tDJKaEF0nCpfNN","b4I5A2NAlG67Y6V0uWsTf4","b4faCsn7RCHZyXCUW4GtTI","b6JGZxaSFO6Lglom1wYe8T","b6c2aO9VdPWaISqRleUCN5","b6sY0WAU9DfZRDLNC06DNE","b8RLRpLJZKkY+Bnge4cwMm","b9J7nui6hBYbcbaztL+myA","b9qNvFbOlChbHOcUrBQ0OV","bcB7igojNO9IzhjAc7d7ud","be89ooKgxOeqAUi0rl/fvD","c4cLb1uNVJUYAXkE+F1jUc","c5CRjIXC9AabegfpDKxxb5","c6Ji4ylPVJ2aReQ69Aa4Wr","ccQQlPjttEU5mrbALvqZvi","ceu5eonFFP06fnNlFqrEB8","cf1t6L8lJA+Z29JHwiAEu2","d1TTM/THZMIpEHCqdBIbD+","d12XyVXR5AF4gmd0nXCkZ5","d2P2xHhENMTaMmvw0lEyaz","d2ascqW2VKvLHayVIJgClg","d3I9XTw7JHiKi5rv75aKT+","d3jqItaFlHw5QAH06uCw4l","d6Oiq10yZKpJtOCpKp0y1v","d7ESrOZnFFwpJxg4h3oWL9","dabr+RAphNSLPGAXH/Ol7Q","dbb7XUOVtNpZVeVP3nHpSg","dbgAJHPQhOb4yzfcAwoxle","deCqc8Cu9I3JhxxGE4F+bz","dfFwND5NJLE7oUqmy1R48k","e0eiyyOmNJw5RKGZ2g7P0+","e1NuquhR1MgoioB7wvfWbD","e3Hg4M9/9GeLoHR+Y+auGe","e5onmWR6JIV6JrOoqFpgDC","e56+KrYg5DuqtpCV/8auZz","e6524K6ohNcY6wGXHdcc0T","e7WgZMivVKurG/mIYG96LT","e8GHtbnZZNF4RH6yeya5kT","eeO+sOss5OF5PDA5lHycx2","efysJ24IlI/rIjFL3e6S5a","ef3YDM3spLyJQmvzTTAb23","f3BCrf5OVH4prxue1gHBYB","f3Suv/h7ZDh5Ci0nrPbIOE","f4ACD/gcJLJ7s4M4qUtrzV","f6NVr+oOpAGJLE19PauRMK","f7nemjgT5FE4BPC2pUEiz5","f9el/AlQhJtoalcG7nxSrq","ffRKVocRtOW4T1MKOCSigP","018PRUTt9Cj5GLJMO/h54Z@6c48a","018PRUTt9Cj5GLJMO/h54Z@f9941","024DRvI19J8aTmIdRBqBeY@6c48a","024DRvI19J8aTmIdRBqBeY@f9941","04VAc0xpJJ1ptKvFLRooAg@6c48a","04VAc0xpJJ1ptKvFLRooAg@f9941","049he3591OkJgCznlaslxz@6c48a","049he3591OkJgCznlaslxz@f9941","06IdNYB9JJYZwGMPSTENR1","07AFMsZKVO37+/sXmEesg9@6c48a","07AFMsZKVO37+/sXmEesg9@f9941","07B8IYmc5P4L4XmAMGtTbY@6c48a","07B8IYmc5P4L4XmAMGtTbY@f9941","08pAzbdhxHEKiAP7tYQRy8@6c48a","08pAzbdhxHEKiAP7tYQRy8@f9941","08/eH0nCpJhZqttBmuOPYz","09Vccspw1PY6bE3KuhfA0Y","0bAPabXRJD9YaZu1gHfM7M","0bQBfQ1npAwJrp+DMJblc9@6c48a","0bQBfQ1npAwJrp+DMJblc9@f9941","0bkSmo+2BDrKkRfzAHutK6@6c48a","0bkSmo+2BDrKkRfzAHutK6@f9941","0bp7ce0W1FV6PsDACZCaw6@6c48a","0bp7ce0W1FV6PsDACZCaw6@f9941","0b4UWB5z9Jy4rL+5tDXhAe@6c48a","0b4UWB5z9Jy4rL+5tDXhAe@f9941","0caVm/t9tJxLycYULRc4j/@6c48a","0caVm/t9tJxLycYULRc4j/@f9941","0ccjOxu51MOLXxFj7agF+y@6c48a","0ccjOxu51MOLXxFj7agF+y@f9941","0ddnlLBHNEx6j3nUroJBHF@6c48a","0ddnlLBHNEx6j3nUroJBHF@f9941","0eWhibAbBJWoVqiwAZmadE","0f8OLmrctPoqKtXoEC2k/D@6c48a","0f8OLmrctPoqKtXoEC2k/D@f9941","10bw9G5vtPUoVgrUaSJnze@6c48a","10bw9G5vtPUoVgrUaSJnze@f9941","10mMiT4wJNGpqeLMnQIkv5@6c48a","10mMiT4wJNGpqeLMnQIkv5@f9941","10na3T2OdOuKtq2tNrx3ag@6c48a","10na3T2OdOuKtq2tNrx3ag@f9941","118a56661","11zZBubK5HOpqXDgioSJpF@6c48a","11zZBubK5HOpqXDgioSJpF@f9941","11zqbnn5RHiraB0y7iUvm1@6c48a","11zqbnn5RHiraB0y7iUvm1@f9941","12qxxQUj5Ft7ZJUsI3iheF@6c48a","12qxxQUj5Ft7ZJUsI3iheF@f9941","12c95efa0","13HoaXf/RKWrqR5WeBBqSE","13432853b","1352dc67f","13a74d1c2","13e91ca31","14B4p4JYBASb7KANH1NuFC@6c48a","14B4p4JYBASb7KANH1NuFC@f9941","1408a0fd6","14Q/JdlY9Km6cL7JOCbxCz@6c48a","14Q/JdlY9Km6cL7JOCbxCz@f9941","1525c08a0","1533031a9","15dJrwvTBBs7iYZWxUQIHJ@6c48a","15dJrwvTBBs7iYZWxUQIHJ@f9941","1589c0603","15jdWpb+9BLLIHNC9oBbgN","16jYjGPlJDub5mnn5dFbeL@6c48a","16jYjGPlJDub5mnn5dFbeL@f9941","16p8T2NLVJI6KjT7eD2oAn@6c48a","16p8T2NLVJI6KjT7eD2oAn@f9941","17Pvml1PZEEZAn/41xZvCv@6c48a","17Pvml1PZEEZAn/41xZvCv@f9941","17tVFptNpKVJaEcxBNvoLs@6c48a","17tVFptNpKVJaEcxBNvoLs@f9941","1921312c7","1931c06ee","19zvPzNwZKOI0Q3E30t25M@6c48a","19zvPzNwZKOI0Q3E30t25M@f9941","194inRvHND27/kFubYzrkR@6c48a","194inRvHND27/kFubYzrkR@f9941","1b3d25a8d","1b5ab3da1","1bfbrErqdJH6FdCxEkCtxh","1b8855288","1be9c6944","1cf/Ig+RtPSLhqSqPNsf4d@6c48a","1cf/Ig+RtPSLhqSqPNsf4d@f9941","1d378af17","1d498ee8f","1e0d73d5a","1eIRkygrZB/pUZEi9JEiAI@6c48a","1eIRkygrZB/pUZEi9JEiAI@f9941","1eI4tuFZRBda+gJ+xHzrwL@6c48a","1eI4tuFZRBda+gJ+xHzrwL@f9941","1eejlSFshL56ItE7IeRMRO","1ejlzSg9ZHWrifJwPM3MsB@6c48a","1ejlzSg9ZHWrifJwPM3MsB@f9941","1ead328a0","1ebe49f9e","1fd95W1NVCFoY3w7hQMq10","1f7g+PENZKuqLAZCseywD2@6c48a","1f7g+PENZKuqLAZCseywD2@f9941","20bbZIQFxOXYRu512svNw6","22ZLBaARJG7YiJGW5XIp/t","24Bm/rFkxNzKf0p0/i/Grt@6c48a","24Bm/rFkxNzKf0p0/i/Grt@f9941","25O/2t6FpK3rKoSiRKh3jm@6c48a","25O/2t6FpK3rKoSiRKh3jm@f9941","255ucEIe1ED7Gj1Q42VhcJ@6c48a","255ucEIe1ED7Gj1Q42VhcJ@f9941","28rtTLiGRLFaw4QcwGTxul@6c48a","28rtTLiGRLFaw4QcwGTxul@f9941","280EX6hnBEGocuv41VC5HF@6c48a","280EX6hnBEGocuv41VC5HF@f9941","2cuLnysahHTpQmA0+eQ8vE","2dTn38B3pPvL/PS/fMiuAl@6c48a","2dTn38B3pPvL/PS/fMiuAl@f9941","31Hl7Sz5dGAKItqiC1wxjH@6c48a","31Hl7Sz5dGAKItqiC1wxjH@f9941","31sqoN33NOeY+yyOGPj9ij","346TkYcXFLtLJDPf67BcId@6c48a","346TkYcXFLtLJDPf67BcId@f9941","38ELtNc1VHaZqwU/Hb8nNg@6c48a","38ELtNc1VHaZqwU/Hb8nNg@f9941","381VKfHH1J85M0BB758RZk","39/JRkDiNJ17DCbSin3049@6c48a","39/JRkDiNJ17DCbSin3049@f9941","3awOIGMN1FkYmqLM1jC8ny@6c48a","3awOIGMN1FkYmqLM1jC8ny@f9941","3bs42tOTlA4IOP0OcdnNOL@6c48a","3bs42tOTlA4IOP0OcdnNOL@f9941","3e5c9HGHFIm5jsNkyH2e26@6c48a","3e5c9HGHFIm5jsNkyH2e26@f9941","3fq3LDyfhLXb+cGFN0hMVL@6c48a","3fq3LDyfhLXb+cGFN0hMVL@f9941","40O90SEYRF8JaE/FzR541O@6c48a","40O90SEYRF8JaE/FzR541O@f9941","42fDL29HtB7Z5eJwF6TVMe","42/VZgJvZIc7CIygR0vztV@6c48a","42/VZgJvZIc7CIygR0vztV@f9941","4327qUD4FMlI9Z3O/IJ0hG","44Af5x21RGbIAm+1h2a6a0","44ZxDN/exLA4h9ON6JKrBJ@6c48a","44ZxDN/exLA4h9ON6JKrBJ@f9941","46fXfR58xPtJ1v0Grxt7Gu","462j9KSPVLI6jxRbrw3bs3@6c48a","462j9KSPVLI6jxRbrw3bs3@f9941","47MVa1p8hLj6xOvh8LuvWs@6c48a","47MVa1p8hLj6xOvh8LuvWs@f9941","47M3zqnvFEooE2CxRe1xSq@6c48a","47M3zqnvFEooE2CxRe1xSq@f9941","48Bl2iEY1Np7OHnwei+dab@6c48a","48Bl2iEY1Np7OHnwei+dab@f9941","48hrsXepJA9oiKZ3PHp3gs","49MkFSP4dEEb7x2SyVNYZH","4ap5jV/IVM/Y+FppM+XDMC","4bFtYoOKFOr5xJBgzzBDhb","4dZ+Q2Sq5CFZoW6b0GeXI8","4dueRlyPtD3Lk2ZSnwWqER@6c48a","4dueRlyPtD3Lk2ZSnwWqER@f9941","50A9GAsmpAeIcwR3nc/e3J","51H0dO4PJJzrwUyrRVCTjh@6c48a","51H0dO4PJJzrwUyrRVCTjh@f9941","51tB9onJ1IMrPSCLHXnMyL@6c48a","51tB9onJ1IMrPSCLHXnMyL@f9941","520hOj+DpInIEUHayOipXY@6c48a","520hOj+DpInIEUHayOipXY@f9941","53S/5wX09MpoOwCU1uQSMc@6c48a","53S/5wX09MpoOwCU1uQSMc@f9941","54CckBeBtPDp1GMWvZxpo6","54T08/inRLTZxe023t8TNH@6c48a","54T08/inRLTZxe023t8TNH@f9941","55MboFgfJKyLJrE6op1KCI@6c48a","55MboFgfJKyLJrE6op1KCI@f9941","56msVAtitBvIoNaNpUn1km@6c48a","56msVAtitBvIoNaNpUn1km@f9941","58mOlm+9lGRKAKj27T9o/w@6c48a","58mOlm+9lGRKAKj27T9o/w@f9941","59eYEdpXdK8K4ADt8QKm0K","59ufF1/IlOwpOY2ue0jPn4@6c48a","59ufF1/IlOwpOY2ue0jPn4@f9941","5aO2kbLn9EoqJvOe/yPENg@6c48a","5aO2kbLn9EoqJvOe/yPENg@f9941","5bA090vLhErZFPQ/PB4Tf5","5cFshZQv1Ju7pJYa4mZi0Q@6c48a","5cFshZQv1Ju7pJYa4mZi0Q@f9941","60h/AID3hA9Z0391NMV7vx@6c48a","60h/AID3hA9Z0391NMV7vx@f9941","60resS1FFJLZ3akQx8HyXu","60vZJn/i9GoaiiOgUd/dWu","61h9DkRUJDy75bzM0QMw1l@6c48a","61h9DkRUJDy75bzM0QMw1l@f9941","62VlLDQ3BE4J1oyQcNg4wv","65NUN7CjVDH61dR86l7cEJ@6c48a","65NUN7CjVDH61dR86l7cEJ@f9941","6630IAVehFEZZcWKU4tqRO","67NNEMsf5O5oYs+4B76VBJ@6c48a","67NNEMsf5O5oYs+4B76VBJ@f9941","6aCm73DIpIwY2ky5m8MXxX@6c48a","6aCm73DIpIwY2ky5m8MXxX@f9941","6bYiI0JipBfaM73qjDhBso@6c48a","6bYiI0JipBfaM73qjDhBso@f9941","6cF7vHaA5K1p7NrN1jW7uf@6c48a","6cF7vHaA5K1p7NrN1jW7uf@f9941","6cGnj12DdClYXjYjR9xqtL@6c48a","6cGnj12DdClYXjYjR9xqtL@f9941","6cbHfQ7nNOyZc0KRmQwo2S@6c48a","6cbHfQ7nNOyZc0KRmQwo2S@f9941","6dwfF3BBNAxqdxN/qnRUPX@6c48a","6dwfF3BBNAxqdxN/qnRUPX@f9941","6d8rMTWvZFm4iORHM4Pr/b","6frla4ojBHJaq8yzrNJJv5@6c48a","6frla4ojBHJaq8yzrNJJv5@f9941","70BI5aKkVMAp5pIJxnqO5/","72cye7QKdM6JWuvwdRp0QB@6c48a","72cye7QKdM6JWuvwdRp0QB@f9941","72/cyFkB5PPYAfyCmhh//g@6c48a","72/cyFkB5PPYAfyCmhh//g@f9941","73O8NapAVB4IF+mJesvxRp","74rxQzEj9N+65F9TNNsFh7@6c48a","74rxQzEj9N+65F9TNNsFh7@f9941","76gtMW8KFGFandI6Ka7IUb@6c48a","76gtMW8KFGFandI6Ka7IUb@f9941","77iZWP67NKKZuePcK+qZBO","78SshxEKFJwrmoi3KSjpNB@6c48a","78SshxEKFJwrmoi3KSjpNB@f9941","78dQhPBptES6+ZGkdvB1aC","79Vgb5vB1FrriLBLEyhG3v@6c48a","79Vgb5vB1FrriLBLEyhG3v@f9941","79+6VKJA5Mj6XWYoCH/8Uv@6c48a","79+6VKJA5Mj6XWYoCH/8Uv@f9941","7a3CK+g5ZDiYt1Zd3iZyl1@6c48a","7a3CK+g5ZDiYt1Zd3iZyl1@f9941","7dBfRtKrlMW7ioRdeMIoBo@6c48a","7dBfRtKrlMW7ioRdeMIoBo@f9941","7fHAPD9d9Kj41JfsX/UakR@6c48a","7fHAPD9d9Kj41JfsX/UakR@f9941","7fmABzGYpNSa/mvYi3mKl+@6c48a","7fmABzGYpNSa/mvYi3mKl+@f9941","82mGVC91FPY5FhTb3UjA4l@6c48a","82mGVC91FPY5FhTb3UjA4l@f9941","83TjcpWBVOZJRtPvLKjK8I@6c48a","83TjcpWBVOZJRtPvLKjK8I@f9941","84eaR3c4ROg5QH+Xt5M2U5@6c48a","84eaR3c4ROg5QH+Xt5M2U5@f9941","84y6nFTMhPOpXnfP35YyOS@6c48a","84y6nFTMhPOpXnfP35YyOS@f9941","85hlrtFApErpxAbGGyu1Jb@6c48a","85hlrtFApErpxAbGGyu1Jb@f9941","88SAD1+BRDrr3+zRWrvbbV@6c48a","88SAD1+BRDrr3+zRWrvbbV@f9941","883ZpDP2BFtJxcCpAYESg5@6c48a","883ZpDP2BFtJxcCpAYESg5@f9941","893Q/s8q1K652gsq9HM7MK@6c48a","893Q/s8q1K652gsq9HM7MK@f9941","8a+W+AwrxOs7Db48nHZCOt@6c48a","8a+W+AwrxOs7Db48nHZCOt@f9941","8cbIGG5gdNHqTRwifewZgo","8cgKoOwHpHva7HhgICBxPT@6c48a","8cgKoOwHpHva7HhgICBxPT@f9941","8c1/QX/FJIDIwNvppKCAMz@6c48a","8c1/QX/FJIDIwNvppKCAMz@f9941","8dKS+bbUpLTIlki3WYTn9l","8dZA18k81DEKwFJpmtZpr/@6c48a","8dZA18k81DEKwFJpmtZpr/@f9941","8eGl04E2lPz7xU0vbm4Nlx@6c48a","8eGl04E2lPz7xU0vbm4Nlx@f9941","90NhT8+4BHhL146ZYJEPQ1","90UJQJdSlPS6OehPrsMe+W","90nLLZpYVNAZew6+lgGkeZ@6c48a","90nLLZpYVNAZew6+lgGkeZ@f9941","91HFE+kURCm7JwtU8egfLi@6c48a","91HFE+kURCm7JwtU8egfLi@f9941","91QF9RqGxEToWdfIHa7Mvp@6c48a","91QF9RqGxEToWdfIHa7Mvp@f9941","91yu6Mx5ZDv640aECHkcMz","92V9AQ2YdHMIhvhb4JTxrV@6c48a","92V9AQ2YdHMIhvhb4JTxrV@f9941","93oaxDDO5BBow6Tv0VO43i@6c48a","93oaxDDO5BBow6Tv0VO43i@f9941","94C817p2VFq6Cc81r4q6AE@6c48a","94C817p2VFq6Cc81r4q6AE@f9941","94OK3+SKxM6rdMfNdzUmXD@6c48a","94OK3+SKxM6rdMfNdzUmXD@f9941","9461nUfTJOuIAOBG8g6uTv@6c48a","9461nUfTJOuIAOBG8g6uTv@f9941","95KzJV0DlJHYtuT/qKbCo9@6c48a","95KzJV0DlJHYtuT/qKbCo9@f9941","95vyTslLpBI5tQMANcZ8yP@6c48a","95vyTslLpBI5tQMANcZ8yP@f9941","96X6we/y5NNadHRN+B2xFs@6c48a","96X6we/y5NNadHRN+B2xFs@f9941","97MRXpX+VJBL0IBUVm+F7w@6c48a","97MRXpX+VJBL0IBUVm+F7w@f9941","98Je2RKg5DeYlcYM96Gnho","98n+XY4UNI86aIQuFYO+O5@6c48a","98n+XY4UNI86aIQuFYO+O5@f9941","99zwxxXtBCK7GNeR/9PeVl","9aSFoxUg1LD5wgAYNPLnt4@6c48a","9aSFoxUg1LD5wgAYNPLnt4@f9941","9bi8YAlu5C+KSA69ZHvDHA@6c48a","9bi8YAlu5C+KSA69ZHvDHA@f9941","9ccAJVTzBCvpuImKuC4/3N@6c48a","9ccAJVTzBCvpuImKuC4/3N@f9941","9e4SsZx9RHBadChj/gdGfv@6c48a","9e4SsZx9RHBadChj/gdGfv@f9941","a0TlVSOehEYpuMaLuqATHy@6c48a","a0TlVSOehEYpuMaLuqATHy@f9941","a2HTN5KLpPSJsXiuGtbV8p","a3NZpbovZMX455Qa2cC9pa@6c48a","a3NZpbovZMX455Qa2cC9pa@f9941","a3XL3P7MZB9LBg9tl99dbZ","a6Lb+LXMNDqaLzEb8lkQfu@6c48a","a6Lb+LXMNDqaLzEb8lkQfu@f9941","a6RA8rtgtO06TayYpLJmBs@6c48a","a6RA8rtgtO06TayYpLJmBs@f9941","a61pM9ihtFXL2rHsHUmAFe@6c48a","a61pM9ihtFXL2rHsHUmAFe@f9941","a7VBRDjyhF7a7P0j7J1uFk","a922Mt06hIL6cJRj6n8nhd@6c48a","a922Mt06hIL6cJRj6n8nhd@f9941","abMztMnytBm47ah3blt0sV@6c48a","abMztMnytBm47ah3blt0sV@f9941","abcdoDpHBKs7IRjXUk2Ova@6c48a","abcdoDpHBKs7IRjXUk2Ova@f9941","acA5QZdh1F37QH7cSXMFph@6c48a","acA5QZdh1F37QH7cSXMFph@f9941","acS5AiBOFO06AZS2Sylwuf","acqB11cnBKt5tClcvHKAAH@6c48a","acqB11cnBKt5tClcvHKAAH@f9941","adz7KhxXNMv4Iryo9vVumm","afZTjzH7ZLc4uYcAcuYMBq@6c48a","afZTjzH7ZLc4uYcAcuYMBq@f9941","afm3nIC4JG5Yn/0ljad8mq","b0ms/x8ltBxLB7/1Y9enwY@6c48a","b0ms/x8ltBxLB7/1Y9enwY@f9941","b2QNILH6tDJKaEF0nCpfNN@6c48a","b2QNILH6tDJKaEF0nCpfNN@f9941","b34toSvBhC8oI5G193o27n","b4I5A2NAlG67Y6V0uWsTf4@6c48a","b4I5A2NAlG67Y6V0uWsTf4@f9941","b4faCsn7RCHZyXCUW4GtTI@6c48a","b4faCsn7RCHZyXCUW4GtTI@f9941","b5GCvAY+dMSYZVbVCmomw9","b6JGZxaSFO6Lglom1wYe8T@6c48a","b6JGZxaSFO6Lglom1wYe8T@f9941","b6c2aO9VdPWaISqRleUCN5@6c48a","b6c2aO9VdPWaISqRleUCN5@f9941","b6sY0WAU9DfZRDLNC06DNE@6c48a","b6sY0WAU9DfZRDLNC06DNE@f9941","b8RLRpLJZKkY+Bnge4cwMm@6c48a","b8RLRpLJZKkY+Bnge4cwMm@f9941","b8V5qU5d1FHpWzunqsRtU9","b9J7nui6hBYbcbaztL+myA@6c48a","b9J7nui6hBYbcbaztL+myA@f9941","b9qNvFbOlChbHOcUrBQ0OV@6c48a","b9qNvFbOlChbHOcUrBQ0OV@f9941","bcB7igojNO9IzhjAc7d7ud@6c48a","bcB7igojNO9IzhjAc7d7ud@f9941","bcXFedObRLLpdIDBlYAkkA","be4VxOCexHM72F3twAwhje","be89ooKgxOeqAUi0rl/fvD@6c48a","be89ooKgxOeqAUi0rl/fvD@f9941","c4cLb1uNVJUYAXkE+F1jUc@6c48a","c4cLb1uNVJUYAXkE+F1jUc@f9941","c5CRjIXC9AabegfpDKxxb5@6c48a","c5CRjIXC9AabegfpDKxxb5@f9941","c6Ji4ylPVJ2aReQ69Aa4Wr@6c48a","c6Ji4ylPVJ2aReQ69Aa4Wr@f9941","c7wQoyIOVG97SNdeSFlzIU","camD8STyNGXIynJqwNpwZ8","ccQQlPjttEU5mrbALvqZvi@6c48a","ccQQlPjttEU5mrbALvqZvi@f9941","ccQvqQNCBG/LTekOX5tM2E","celsYdqe5F16g5yiURcbSf","ceu5eonFFP06fnNlFqrEB8@6c48a","ceu5eonFFP06fnNlFqrEB8@f9941","cf1t6L8lJA+Z29JHwiAEu2@6c48a","cf1t6L8lJA+Z29JHwiAEu2@f9941","d1H7P8JuZNn4vZFU3yIo2s","d1TTM/THZMIpEHCqdBIbD+@6c48a","d1TTM/THZMIpEHCqdBIbD+@f9941","d12XyVXR5AF4gmd0nXCkZ5@6c48a","d12XyVXR5AF4gmd0nXCkZ5@f9941","d2P2xHhENMTaMmvw0lEyaz@6c48a","d2P2xHhENMTaMmvw0lEyaz@f9941","d2ascqW2VKvLHayVIJgClg@6c48a","d2ascqW2VKvLHayVIJgClg@f9941","d3I9XTw7JHiKi5rv75aKT+@6c48a","d3I9XTw7JHiKi5rv75aKT+@f9941","d3jqItaFlHw5QAH06uCw4l@6c48a","d3jqItaFlHw5QAH06uCw4l@f9941","d4g9n+7wlAu5fefScHhkmq","d6Oiq10yZKpJtOCpKp0y1v@6c48a","d6Oiq10yZKpJtOCpKp0y1v@f9941","d7ESrOZnFFwpJxg4h3oWL9@6c48a","d7ESrOZnFFwpJxg4h3oWL9@f9941","d7zl/QyvdC7YtBRYFBQMkL","dabr+RAphNSLPGAXH/Ol7Q@6c48a","dabr+RAphNSLPGAXH/Ol7Q@f9941","dbb7XUOVtNpZVeVP3nHpSg@6c48a","dbb7XUOVtNpZVeVP3nHpSg@f9941","dcHgZnoGVHAbu/fbhkS3bn","deCqc8Cu9I3JhxxGE4F+bz@6c48a","deCqc8Cu9I3JhxxGE4F+bz@f9941","deanPdMOpBxKh73gA3Wlpc","dfFwND5NJLE7oUqmy1R48k@6c48a","dfFwND5NJLE7oUqmy1R48k@f9941","e0eiyyOmNJw5RKGZ2g7P0+@6c48a","e0eiyyOmNJw5RKGZ2g7P0+@f9941","e1NuquhR1MgoioB7wvfWbD@6c48a","e1NuquhR1MgoioB7wvfWbD@f9941","e3Hg4M9/9GeLoHR+Y+auGe@6c48a","e3Hg4M9/9GeLoHR+Y+auGe@f9941","e5onmWR6JIV6JrOoqFpgDC@6c48a","e5onmWR6JIV6JrOoqFpgDC@f9941","e56+KrYg5DuqtpCV/8auZz@6c48a","e56+KrYg5DuqtpCV/8auZz@f9941","e6524K6ohNcY6wGXHdcc0T@6c48a","e6524K6ohNcY6wGXHdcc0T@f9941","e7WgZMivVKurG/mIYG96LT@6c48a","e7WgZMivVKurG/mIYG96LT@f9941","e8GHtbnZZNF4RH6yeya5kT@6c48a","e8GHtbnZZNF4RH6yeya5kT@f9941","ea6j+WSARCJLX4Flh/SCLJ","eeO+sOss5OF5PDA5lHycx2@6c48a","eeO+sOss5OF5PDA5lHycx2@f9941","efysJ24IlI/rIjFL3e6S5a@6c48a","efysJ24IlI/rIjFL3e6S5a@f9941","ef3YDM3spLyJQmvzTTAb23@6c48a","ef3YDM3spLyJQmvzTTAb23@f9941","ef6JXDA5dNl6yq3DsYhoCK","f3BCrf5OVH4prxue1gHBYB@6c48a","f3BCrf5OVH4prxue1gHBYB@f9941","f3Suv/h7ZDh5Ci0nrPbIOE@6c48a","f3Suv/h7ZDh5Ci0nrPbIOE@f9941","f4ACD/gcJLJ7s4M4qUtrzV@6c48a","f4ACD/gcJLJ7s4M4qUtrzV@f9941","f5M8zEOLBBk5jgTjzIEPUt","f6NVr+oOpAGJLE19PauRMK@6c48a","f6NVr+oOpAGJLE19PauRMK@f9941","f6vH5hLjFMYJor+Ax2urYG","f9el/AlQhJtoalcG7nxSrq@6c48a","f9el/AlQhJtoalcG7nxSrq@f9941","fcANA9jItHHaqoUQeAHvXk","fdvSUG1eNCmKQF4DNbn+YM","ffRKVocRtOW4T1MKOCSigP@6c48a","ffRKVocRtOW4T1MKOCSigP@f9941","01a1c8659","01ea73c33","0219915ad","02bc49aab","0306cc690","04af92fa9","04f8fa2b5","04fd8f778","07a21daa9","07def267d","0a1a24613","0a2017d08","0a90ec573","0aa964105","0b4848268","0b5af1751","0bd7ee6a7","0c277fb22","0c6a35750","0dedf8190","0e25c4090","0e5df3606","0ecf44f96","0f1b89258","0f74329ac","118a56661@6c48a","12c95efa0@6c48a","13432853b@6c48a","1352dc67f@6c48a","13a74d1c2@6c48a","13e91ca31@6c48a","1408a0fd6@6c48a","1525c08a0@6c48a","1533031a9@6c48a","1589c0603@6c48a","1921312c7@6c48a","1931c06ee@6c48a","1b3d25a8d@6c48a","1b5ab3da1@6c48a","1b8855288@6c48a","1be9c6944@6c48a","1d378af17@6c48a","1d498ee8f@6c48a","1e0d73d5a@6c48a","1ead328a0@6c48a","1ebe49f9e@6c48a","44Ov7arnpFIauR0cyfvUV2","6bg69PUqRGx4y6ImrVcLit"],"paths":{"0":["res/bullet10180/ani",5],"1":["res/bullet1052/ani",5],"2":["res/bullet21/ani",5],"3":["res/bullet20/ani",5],"4":["res/bullet1103/ani",5],"5":["res/bullet10200/ani",5],"6":["res/bullet1042/ani",5],"7":["res/bullet12/ani",5],"8":["res/bullet1054/ani",5],"9":["res/bullet22/ani",5],"10":["res/bullet1044/ani",5],"11":["res/bullet9/ani",5],"12":["res/bullet1106/ani",5],"13":["res/bullet1081/ani",5],"14":["res/bullet1082/ani",5],"15":["res/bullet8/ani",5],"16":["res/bullet1091/ani",5],"17":["res/bullet1031",2],"18":["res/bullet1054/skeleton-4 05",2],"19":["res/bullet10200/ww12",2],"20":["res/bullet10200/ww5",2],"21":["res/bullet21/jgq-b 05",2],"22":["res/bullet21/jgq-b 02",2],"23":["res/bullet10200/ww2",2],"24":["res/bullet1044/ddd3",2],"25":["res/bullet10190",2],"26":["res/bullet1071",2],"27":["res/bullet1091/zuan-animation 0",2],"28":["res/bullet22/xing-animation 01",2],"29":["res/bullet1101",2],"30":["res/bullet1091/zuan-animation 3",2],"31":["res/bullet22/xing-animation 00",2],"32":["res/bullet12/4",2],"33":["res/bullet20/jgq-a 0",2],"34":["res/bullet1044/ddd8",2],"35":["res/bullet10180/s1",2],"36":["res/bullet5",2],"37":["res/bullet16/5",2],"38":["res/bullet12/2",2],"39":["res/bullet1062",2],"40":["res/bullet22/xing-animation 07",2],"41":["res/bullet10160",2],"42":["res/bullet1052/skeleton-3 13",2],"43":["res/bullet1082/sd-huang-1 02",2],"44":["res/bullet1081/sd-lv-1 08",2],"45":["res/bullet10180/s5",2],"46":["res/bullet8/2",2],"47":["res/bullet8/3",2],"48":["res/bullet1071/center",2],"49":["res/bullet1052/skeleton-3 06",2],"50":["res/bullet1053",2],"51":["res/bullet1042/huo-5 06",2],"52":["res/bullet1054/skeleton-4 10",2],"53":["res/bullet22/xing-animation 09",2],"54":["res/bullet1082/sd-huang-1 06",2],"55":["res/bullet22/xing-animation 02",2],"56":["res/bullet1081/sd-lv-1 03",2],"57":["res/bullet1054/skeleton-4 09",2],"58":["res/bullet10200/ww1",2],"59":["res/bullet10140",2],"60":["res/bullet16/8",2],"61":["res/bullet21/jgq-b 14",2],"62":["res/bullet21/jgq-b 01",2],"63":["res/bullet1082/sd-huang-1 11",2],"64":["res/bullet21/jgq-b 15",2],"65":["res/bullet1042/huo-5 04",2],"66":["res/bullet22/xing-animation 11",2],"67":["res/bullet1044/ddd1",2],"68":["res/bullet13",2],"69":["res/bullet1042/huo-5 07",2],"70":["res/bullet9/qqa4",2],"71":["res/bullet21/jgq-b 00",2],"72":["res/bullet1051_1",2],"73":["res/bullet1081/sd-lv-1 02",2],"74":["res/bullet1102",2],"75":["res/bullet1011",2],"76":["res/bullet1042/huo-5 03",2],"77":["res/bullet1054/skeleton-4 02",2],"78":["res/bullet21/jgq-b 04",2],"79":["res/bullet21/jgq-b 07",2],"80":["res/bullet22/xing-animation 08",2],"81":["res/bullet1022",2],"82":["res/bullet10200/ww3",2],"83":["res/bullet6",2],"84":["res/bullet20/jgq-a 6",2],"85":["res/bullet16/2",2],"86":["res/bullet21/jgq-b 13",2],"87":["res/bullet1082/sd-huang-1 05",2],"88":["res/bullet1082/sd-huang-1 09",2],"89":["res/bullet1081/sd-lv-1 07",2],"90":["res/bullet17/rlsz",6],"91":["res/bullet1052/skeleton-3 09",2],"92":["res/bullet16/7",2],"93":["res/bullet21/jgq-b 06",2],"94":["res/bullet1052/skeleton-3 02",2],"95":["res/bullet1081/sd-lv-1 10",2],"96":["res/bullet9/qqa1",2],"97":["res/bullet10200/ww9",2],"98":["res/bullet1052/skeleton-3 10",2],"99":["res/bullet22/xing-animation 04",2],"100":["res/bullet10180/s0",2],"101":["res/bullet1053_1",2],"102":["res/bullet1044/ddd6",2],"103":["res/bullet1081/sd-lv-1 06",2],"104":["res/bullet1082/bullet1082",1],"105":["res/bullet22/xing-animation 05",2],"106":["res/bullet21/jgq-b 08",2],"107":["res/bullet12/3",2],"108":["res/bullet1052/skeleton-3 12",2],"109":["res/bullet1061",2],"110":["res/bullet10120",2],"111":["res/bullet16/1",2],"112":["res/bullet9/qqa2",2],"113":["res/bullet10150",2],"114":["res/bullet9/qqa0",2],"115":["res/bullet1042/huo-5 02",2],"116":["res/bullet22/xing-animation 06",2],"117":["res/bullet8/4",2],"118":["res/bullet1021",2],"119":["res/bullet1",2],"120":["res/bullet16/3",2],"121":["res/bullet1081/bullet1081",1],"122":["res/bullet22/xing-animation 03",2],"123":["res/bullet1044/ddd5",2],"124":["res/bullet1082/sd-huang-1 08",2],"125":["res/bullet20/jgq-a 2",2],"126":["res/bullet1044/ddd4",2],"127":["res/bullet1091/zuan-animation 4",2],"128":["res/bullet1081/sd-lv-1 11",2],"129":["res/bullet1042/huo-5 00",2],"130":["res/bullet15",2],"131":["res/bullet20/jgq-a 3",2],"132":["res/bullet12/1",2],"133":["res/bullet20/jgq-a 4",2],"134":["res/bullet17/rlsz",2],"135":["res/bullet1091",2],"136":["res/bullet16/ani",5],"137":["res/bullet1081/sd-lv-1 09",2],"138":["res/bullet1044/ddd7",2],"139":["res/bullet1081/sd-lv-1 04",2],"140":["res/bullet1071/frame",2],"141":["res/bullet10200/ww8",2],"142":["res/bullet1052/skeleton-3 05",2],"143":["res/bullet1052/skeleton-3 04",2],"144":["res/bullet1091/zuan-animation 6",2],"145":["res/bullet1054/skeleton-4 08",2],"146":["res/bullet9/qqa5",2],"147":["res/bullet1012",2],"148":["res/bullet1041",2],"149":["res/bullet1091/zuan-animation 2",2],"150":["res/bullet16",2],"151":["res/dot",2],"152":["res/bullet1091/zuan-animation 1",2],"153":["res/bullet21/jgq-b 09",2],"154":["res/bullet10180/s2",2],"155":["res/bullet1081",2],"156":["res/bullet22",2],"157":["res/bullet1051",2],"158":["res/bullet22/xing-animation 10",2],"159":["res/bullet1082/sd-huang-1 03",2],"160":["res/bullet10180/s3",2],"161":["res/bullet1091/zuan-animation 5",2],"162":["res/bullet3",2],"163":["res/bullet10200/ww11",2],"164":["res/bullet1054/skeleton-4 06",2],"165":["res/bullet1081/sd-lv-1 05",2],"166":["res/bullet9/qqa3",2],"167":["res/bullet16/4",2],"168":["res/bullet1043",2],"169":["res/tail2",2],"170":["res/bullet21/jgq-b 11",2],"171":["res/bullet1105",2],"172":["res/bullet16/6",2],"173":["res/bullet10200/ww6",2],"174":["res/bullet10200/ww10",2],"175":["res/bullet10170",2],"176":["res/bullet4",2],"177":["res/bullet1044/ddd2",2],"178":["res/bullet10200/ww7",2],"179":["res/bullet10200/ww4",2],"180":["res/bullet1054/bullet1054",1],"181":["res/bullet21/jgq-b 10",2],"182":["res/bullet2",2],"183":["res/bullet20/jgq-a 1",2],"184":["res/bullet10180/s4",2],"185":["res/bullet10130",2],"186":["res/bullet21/jgq-b 12",2],"187":["res/bullet21/jgq-b 03",2],"188":["res/bullet1052/skeleton-3 08",2],"189":["res/bullet1082/sd-huang-1 07",2],"190":["res/tail1",2],"191":["res/bullet1042/huo-5 08",2],"192":["res/bullet1104",2],"193":["res/bullet1082/sd-huang-1 04",2],"194":["res/bullet8/1",2],"195":["res/bullet1082/sd-huang-1 10",2],"196":["res/bullet1054/skeleton-4 13",2],"197":["res/bullet1054/skeleton-4 04",2],"199":["res/bullet20/jgq-a 5",2],"200":["res/bullet1054/skeleton-4 12",2],"201":["res/bullet1031/texture",3,1],"202":["res/bullet1031/spriteFrame",4,1],"203":["res/bullet1054/skeleton-4 05/texture",3,1],"204":["res/bullet1054/skeleton-4 05/spriteFrame",4,1],"205":["res/bullet10200/ww12/texture",3,1],"206":["res/bullet10200/ww12/spriteFrame",4,1],"207":["res/bullet10200/ww5/texture",3,1],"208":["res/bullet10200/ww5/spriteFrame",4,1],"209":["bullet1011",0],"210":["res/bullet21/jgq-b 05/texture",3,1],"211":["res/bullet21/jgq-b 05/spriteFrame",4,1],"212":["res/bullet21/jgq-b 02/texture",3,1],"213":["res/bullet21/jgq-b 02/spriteFrame",4,1],"214":["res/bullet10200/ww2/texture",3,1],"215":["res/bullet10200/ww2/spriteFrame",4,1],"216":["bullet1103",0],"217":["bullet1081",0],"218":["bullet16",0],"219":["res/bullet1044/ddd3/texture",3,1],"220":["res/bullet1044/ddd3/spriteFrame",4,1],"221":["res/bullet10190/texture",3,1],"222":["res/bullet10190/spriteFrame",4,1],"223":["res/bullet1071/texture",3,1],"224":["res/bullet1071/spriteFrame",4,1],"225":["res/bullet1091/zuan-animation 0/texture",3,1],"226":["res/bullet1091/zuan-animation 0/spriteFrame",4,1],"227":["res/bullet22/xing-animation 01/texture",3,1],"228":["res/bullet22/xing-animation 01/spriteFrame",4,1],"229":["res/bullet1101/texture",3,1],"230":["res/bullet1101/spriteFrame",4,1],"231":["res/bullet1091/zuan-animation 3/texture",3,1],"232":["res/bullet1091/zuan-animation 3/spriteFrame",4,1],"233":["res/bullet10180/bullet10180",1],"234":["res/bullet22/xing-animation 00/texture",3,1],"235":["res/bullet22/xing-animation 00/spriteFrame",4,1],"236":["res/bullet12/4/texture",3,1],"237":["res/bullet12/4/spriteFrame",4,1],"238":["res/bullet20/jgq-a 0/texture",3,1],"239":["res/bullet20/jgq-a 0/spriteFrame",4,1],"240":["res/bullet1044/ddd8/texture",3,1],"241":["res/bullet1044/ddd8/spriteFrame",4,1],"243":["res/bullet10180/s1/texture",3,1],"244":["res/bullet10180/s1/spriteFrame",4,1],"245":["res/bullet5/texture",3,1],"246":["res/bullet5/spriteFrame",4,1],"247":["res/bullet16/5/texture",3,1],"248":["res/bullet16/5/spriteFrame",4,1],"250":["bullet22",0],"255":["res/bullet12/2/texture",3,1],"256":["res/bullet12/2/spriteFrame",4,1],"258":["res/bullet1062/texture",3,1],"259":["res/bullet1062/spriteFrame",4,1],"262":["res/bullet22/xing-animation 07/texture",3,1],"263":["res/bullet22/xing-animation 07/spriteFrame",4,1],"265":["bullet10160",0],"266":["res/bullet10160/texture",3,1],"267":["res/bullet10160/spriteFrame",4,1],"268":["res/bullet1052/skeleton-3 13/texture",3,1],"269":["res/bullet1052/skeleton-3 13/spriteFrame",4,1],"270":["res/bullet1082/sd-huang-1 02/texture",3,1],"271":["res/bullet1082/sd-huang-1 02/spriteFrame",4,1],"272":["res/bullet1081/sd-lv-1 08/texture",3,1],"273":["res/bullet1081/sd-lv-1 08/spriteFrame",4,1],"276":["res/bullet10180/s5/texture",3,1],"277":["res/bullet10180/s5/spriteFrame",4,1],"278":["res/bullet8/2/texture",3,1],"279":["res/bullet8/2/spriteFrame",4,1],"282":["bullet10180",0],"285":["res/bullet8/3/texture",3,1],"286":["res/bullet8/3/spriteFrame",4,1],"290":["res/bullet1071/center/texture",3,1],"291":["res/bullet1071/center/spriteFrame",4,1],"292":["res/bullet1052/skeleton-3 06/texture",3,1],"293":["res/bullet1052/skeleton-3 06/spriteFrame",4,1],"294":["bullet14",0],"295":["res/bullet1053/texture",3,1],"296":["res/bullet1053/spriteFrame",4,1],"299":["bullet1022",0],"300":["res/bullet1042/huo-5 06/texture",3,1],"301":["res/bullet1042/huo-5 06/spriteFrame",4,1],"302":["bullet1044",0],"303":["bullet10190",0],"304":["res/bullet1054/skeleton-4 10/texture",3,1],"305":["res/bullet1054/skeleton-4 10/spriteFrame",4,1],"306":["res/bullet22/xing-animation 09/texture",3,1],"307":["res/bullet22/xing-animation 09/spriteFrame",4,1],"308":["res/bullet1082/sd-huang-1 06/texture",3,1],"309":["res/bullet1082/sd-huang-1 06/spriteFrame",4,1],"310":["res/bullet22/xing-animation 02/texture",3,1],"311":["res/bullet22/xing-animation 02/spriteFrame",4,1],"312":["res/bullet1081/sd-lv-1 03/texture",3,1],"313":["res/bullet1081/sd-lv-1 03/spriteFrame",4,1],"314":["bullet10200",0],"315":["res/bullet1054/skeleton-4 09/texture",3,1],"316":["res/bullet1054/skeleton-4 09/spriteFrame",4,1],"317":["res/bullet10200/ww1/texture",3,1],"318":["res/bullet10200/ww1/spriteFrame",4,1],"319":["res/bullet1042/bullet1042",1],"320":["res/bullet10140/texture",3,1],"321":["res/bullet10140/spriteFrame",4,1],"322":["res/bullet16/8/texture",3,1],"323":["res/bullet16/8/spriteFrame",4,1],"324":["bullet4",0],"325":["res/bullet21/jgq-b 14/texture",3,1],"326":["res/bullet21/jgq-b 14/spriteFrame",4,1],"327":["res/bullet21/jgq-b 01/texture",3,1],"328":["res/bullet21/jgq-b 01/spriteFrame",4,1],"329":["res/bullet1082/sd-huang-1 11/texture",3,1],"330":["res/bullet1082/sd-huang-1 11/spriteFrame",4,1],"331":["res/bullet21/jgq-b 15/texture",3,1],"332":["res/bullet21/jgq-b 15/spriteFrame",4,1],"333":["res/bullet1042/huo-5 04/texture",3,1],"334":["res/bullet1042/huo-5 04/spriteFrame",4,1],"335":["res/bullet22/xing-animation 11/texture",3,1],"336":["res/bullet22/xing-animation 11/spriteFrame",4,1],"337":["bullet8",0],"338":["res/bullet1044/ddd1/texture",3,1],"339":["res/bullet1044/ddd1/spriteFrame",4,1],"340":["bullet1101",0],"341":["res/bullet16/bullet16",1],"342":["res/bullet13/texture",3,1],"343":["res/bullet13/spriteFrame",4,1],"344":["bullet1042",0],"345":["res/bullet1042/huo-5 07/texture",3,1],"346":["res/bullet1042/huo-5 07/spriteFrame",4,1],"347":["res/bullet9/qqa4/texture",3,1],"348":["res/bullet9/qqa4/spriteFrame",4,1],"349":["res/bullet21/jgq-b 00/texture",3,1],"350":["res/bullet21/jgq-b 00/spriteFrame",4,1],"351":["res/bullet1051_1/texture",3,1],"352":["res/bullet1051_1/spriteFrame",4,1],"353":["bullet10120",0],"354":["bullet20",0],"355":["res/bullet21/bullet21",1],"356":["bullet1",0],"357":["bullet1051",0],"358":["res/bullet1081/sd-lv-1 02/texture",3,1],"359":["res/bullet1081/sd-lv-1 02/spriteFrame",4,1],"360":["bullet19",0],"361":["res/bullet1102/texture",3,1],"362":["res/bullet1102/spriteFrame",4,1],"363":["res/bullet1011/texture",3,1],"364":["res/bullet1011/spriteFrame",4,1],"365":["res/bullet1042/huo-5 03/texture",3,1],"366":["res/bullet1042/huo-5 03/spriteFrame",4,1],"367":["res/bullet1054/skeleton-4 02/texture",3,1],"368":["res/bullet1054/skeleton-4 02/spriteFrame",4,1],"369":["bullet12",0],"370":["res/bullet21/jgq-b 04/texture",3,1],"371":["res/bullet21/jgq-b 04/spriteFrame",4,1],"372":["res/bullet21/jgq-b 07/texture",3,1],"373":["res/bullet21/jgq-b 07/spriteFrame",4,1],"374":["res/bullet22/xing-animation 08/texture",3,1],"375":["res/bullet22/xing-animation 08/spriteFrame",4,1],"376":["res/bullet1022/texture",3,1],"377":["res/bullet1022/spriteFrame",4,1],"378":["bullet1105",0],"379":["res/bullet10200/ww3/texture",3,1],"380":["res/bullet10200/ww3/spriteFrame",4,1],"381":["res/bullet6/texture",3,1],"382":["res/bullet6/spriteFrame",4,1],"383":["bullet3",0],"384":["res/bullet20/jgq-a 6/texture",3,1],"385":["res/bullet20/jgq-a 6/spriteFrame",4,1],"386":["res/bullet16/2/texture",3,1],"387":["res/bullet16/2/spriteFrame",4,1],"388":["bullet7",0],"389":["bullet1041",0],"390":["res/bullet21/jgq-b 13/texture",3,1],"391":["res/bullet21/jgq-b 13/spriteFrame",4,1],"392":["bullet21",0],"393":["res/bullet1082/sd-huang-1 05/texture",3,1],"394":["res/bullet1082/sd-huang-1 05/spriteFrame",4,1],"395":["res/bullet1091/bullet1091",1],"396":["res/bullet1082/sd-huang-1 09/texture",3,1],"397":["res/bullet1082/sd-huang-1 09/spriteFrame",4,1],"398":["res/bullet1081/sd-lv-1 07/texture",3,1],"399":["res/bullet1081/sd-lv-1 07/spriteFrame",4,1],"400":["res/bullet1052/skeleton-3 09/texture",3,1],"401":["res/bullet1052/skeleton-3 09/spriteFrame",4,1],"402":["res/bullet16/7/texture",3,1],"403":["res/bullet16/7/spriteFrame",4,1],"404":["res/bullet21/jgq-b 06/texture",3,1],"405":["res/bullet21/jgq-b 06/spriteFrame",4,1],"406":["res/bullet1052/skeleton-3 02/texture",3,1],"407":["res/bullet1052/skeleton-3 02/spriteFrame",4,1],"408":["res/bullet1081/sd-lv-1 10/texture",3,1],"409":["res/bullet1081/sd-lv-1 10/spriteFrame",4,1],"410":["bullet2",0],"411":["res/bullet9/qqa1/texture",3,1],"412":["res/bullet9/qqa1/spriteFrame",4,1],"413":["bullet1104",0],"414":["res/bullet10200/ww9/texture",3,1],"415":["res/bullet10200/ww9/spriteFrame",4,1],"416":["res/bullet1052/skeleton-3 10/texture",3,1],"417":["res/bullet1052/skeleton-3 10/spriteFrame",4,1],"418":["res/bullet1071/bullet1071",1],"419":["res/bullet22/xing-animation 04/texture",3,1],"420":["res/bullet22/xing-animation 04/spriteFrame",4,1],"421":["res/bullet10180/s0/texture",3,1],"422":["res/bullet10180/s0/spriteFrame",4,1],"423":["bullet1102",0],"424":["res/bullet1053_1/texture",3,1],"425":["res/bullet1053_1/spriteFrame",4,1],"426":["bullet1043",0],"427":["res/bullet1044/ddd6/texture",3,1],"428":["res/bullet1044/ddd6/spriteFrame",4,1],"429":["res/bullet1081/sd-lv-1 06/texture",3,1],"430":["res/bullet1081/sd-lv-1 06/spriteFrame",4,1],"431":["res/bullet22/xing-animation 05/texture",3,1],"432":["res/bullet22/xing-animation 05/spriteFrame",4,1],"433":["res/bullet21/jgq-b 08/texture",3,1],"434":["res/bullet21/jgq-b 08/spriteFrame",4,1],"435":["res/bullet12/3/texture",3,1],"436":["res/bullet12/3/spriteFrame",4,1],"437":["res/bullet1052/skeleton-3 12/texture",3,1],"438":["res/bullet1052/skeleton-3 12/spriteFrame",4,1],"439":["res/bullet1061/texture",3,1],"440":["res/bullet1061/spriteFrame",4,1],"441":["res/bullet10120/texture",3,1],"442":["res/bullet10120/spriteFrame",4,1],"443":["res/bullet16/1/texture",3,1],"444":["res/bullet16/1/spriteFrame",4,1],"445":["res/bullet9/qqa2/texture",3,1],"446":["res/bullet9/qqa2/spriteFrame",4,1],"447":["res/bullet10150/texture",3,1],"448":["res/bullet10150/spriteFrame",4,1],"449":["res/bullet9/qqa0/texture",3,1],"450":["res/bullet9/qqa0/spriteFrame",4,1],"451":["res/bullet1042/huo-5 02/texture",3,1],"452":["res/bullet1042/huo-5 02/spriteFrame",4,1],"453":["res/bullet22/xing-animation 06/texture",3,1],"454":["res/bullet22/xing-animation 06/spriteFrame",4,1],"455":["res/bullet8/4/texture",3,1],"456":["res/bullet8/4/spriteFrame",4,1],"457":["bullet1031",0],"458":["res/bullet1021/texture",3,1],"459":["res/bullet1021/spriteFrame",4,1],"460":["res/bullet1/texture",3,1],"461":["res/bullet1/spriteFrame",4,1],"462":["res/bullet1052/bullet1052",1],"463":["res/bullet16/3/texture",3,1],"464":["res/bullet16/3/spriteFrame",4,1],"465":["res/bullet22/xing-animation 03/texture",3,1],"466":["res/bullet22/xing-animation 03/spriteFrame",4,1],"467":["res/bullet17/rlsz",7],"468":["bullet10140",0],"469":["res/bullet1044/ddd5/texture",3,1],"470":["res/bullet1044/ddd5/spriteFrame",4,1],"471":["res/bullet1082/sd-huang-1 08/texture",3,1],"472":["res/bullet1082/sd-huang-1 08/spriteFrame",4,1],"473":["res/bullet20/jgq-a 2/texture",3,1],"474":["res/bullet20/jgq-a 2/spriteFrame",4,1],"475":["res/bullet10200/bullet10200",1],"476":["res/bullet1044/ddd4/texture",3,1],"477":["res/bullet1044/ddd4/spriteFrame",4,1],"478":["res/bullet1091/zuan-animation 4/texture",3,1],"479":["res/bullet1091/zuan-animation 4/spriteFrame",4,1],"480":["res/bullet1081/sd-lv-1 11/texture",3,1],"481":["res/bullet1081/sd-lv-1 11/spriteFrame",4,1],"482":["res/bullet1042/huo-5 00/texture",3,1],"483":["res/bullet1042/huo-5 00/spriteFrame",4,1],"484":["res/bullet15/texture",3,1],"485":["res/bullet15/spriteFrame",4,1],"486":["res/bullet20/jgq-a 3/texture",3,1],"487":["res/bullet20/jgq-a 3/spriteFrame",4,1],"488":["res/bullet12/1/texture",3,1],"489":["res/bullet12/1/spriteFrame",4,1],"490":["res/bullet20/jgq-a 4/texture",3,1],"491":["res/bullet20/jgq-a 4/spriteFrame",4,1],"492":["res/bullet17/rlsz/texture",3,1],"493":["res/bullet17/rlsz/spriteFrame",4,1],"494":["bullet18",0],"495":["res/bullet1091/texture",3,1],"496":["res/bullet1091/spriteFrame",4,1],"497":["bullet1012",0],"498":["res/bullet1081/sd-lv-1 09/texture",3,1],"499":["res/bullet1081/sd-lv-1 09/spriteFrame",4,1],"500":["res/bullet1044/ddd7/texture",3,1],"501":["res/bullet1044/ddd7/spriteFrame",4,1],"502":["res/bullet1081/sd-lv-1 04/texture",3,1],"503":["res/bullet1081/sd-lv-1 04/spriteFrame",4,1],"504":["res/bullet1071/frame/texture",3,1],"505":["res/bullet1071/frame/spriteFrame",4,1],"506":["res/bullet10200/ww8/texture",3,1],"507":["res/bullet10200/ww8/spriteFrame",4,1],"508":["bullet9",0],"509":["res/bullet1052/skeleton-3 05/texture",3,1],"510":["res/bullet1052/skeleton-3 05/spriteFrame",4,1],"511":["res/bullet22/bullet22",1],"512":["res/bullet1052/skeleton-3 04/texture",3,1],"513":["res/bullet1052/skeleton-3 04/spriteFrame",4,1],"514":["res/bullet1091/zuan-animation 6/texture",3,1],"515":["res/bullet1091/zuan-animation 6/spriteFrame",4,1],"516":["res/bullet1054/skeleton-4 08/texture",3,1],"517":["res/bullet1054/skeleton-4 08/spriteFrame",4,1],"518":["bullet5",0],"519":["res/bullet9/qqa5/texture",3,1],"520":["res/bullet9/qqa5/spriteFrame",4,1],"521":["res/bullet1012/texture",3,1],"522":["res/bullet1012/spriteFrame",4,1],"523":["res/bullet1041/texture",3,1],"524":["res/bullet1041/spriteFrame",4,1],"525":["res/bullet1091/zuan-animation 2/texture",3,1],"526":["res/bullet1091/zuan-animation 2/spriteFrame",4,1],"527":["bullet10130",0],"528":["res/bullet16/texture",3,1],"529":["res/bullet16/spriteFrame",4,1],"530":["res/bullet9/bullet9",1],"531":["res/dot/texture",3,1],"532":["res/dot/spriteFrame",4,1],"533":["bullet1053",0],"534":["res/bullet1091/zuan-animation 1/texture",3,1],"535":["res/bullet1091/zuan-animation 1/spriteFrame",4,1],"536":["res/bullet21/jgq-b 09/texture",3,1],"537":["res/bullet21/jgq-b 09/spriteFrame",4,1],"538":["res/bullet",1],"539":["res/bullet10180/s2/texture",3,1],"540":["res/bullet10180/s2/spriteFrame",4,1],"541":["res/bullet1081/texture",3,1],"542":["res/bullet1081/spriteFrame",4,1],"543":["bullet1054",0],"544":["res/bullet22/texture",3,1],"545":["res/bullet22/spriteFrame",4,1],"546":["res/bullet1051/texture",3,1],"547":["res/bullet1051/spriteFrame",4,1],"548":["res/bullet22/xing-animation 10/texture",3,1],"549":["res/bullet22/xing-animation 10/spriteFrame",4,1],"550":["res/bullet1082/sd-huang-1 03/texture",3,1],"551":["res/bullet1082/sd-huang-1 03/spriteFrame",4,1],"552":["bullet13",0],"553":["res/bullet10180/s3/texture",3,1],"554":["res/bullet10180/s3/spriteFrame",4,1],"555":["res/bullet1091/zuan-animation 5/texture",3,1],"556":["res/bullet1091/zuan-animation 5/spriteFrame",4,1],"557":["res/bullet3/texture",3,1],"558":["res/bullet3/spriteFrame",4,1],"559":["res/bullet8/bullet8",1],"560":["bullet1091",0],"561":["res/bullet10200/ww11/texture",3,1],"562":["res/bullet10200/ww11/spriteFrame",4,1],"563":["res/bullet1054/skeleton-4 06/texture",3,1],"564":["res/bullet1054/skeleton-4 06/spriteFrame",4,1],"565":["res/bullet1081/sd-lv-1 05/texture",3,1],"566":["res/bullet1081/sd-lv-1 05/spriteFrame",4,1],"567":["res/bullet9/qqa3/texture",3,1],"568":["res/bullet9/qqa3/spriteFrame",4,1],"569":["bullet1071",0],"570":["bullet1062",0],"571":["res/bullet16/4/texture",3,1],"572":["res/bullet16/4/spriteFrame",4,1],"573":["res/bullet12/bullet12",1],"574":["bullet1106",0],"575":["res/bullet1043/texture",3,1],"576":["res/bullet1043/spriteFrame",4,1],"577":["res/tail2/texture",3,1],"578":["res/tail2/spriteFrame",4,1],"579":["bullet10150",0],"580":["res/bullet21/jgq-b 11/texture",3,1],"581":["res/bullet21/jgq-b 11/spriteFrame",4,1],"582":["res/bullet1105/texture",3,1],"583":["res/bullet1105/spriteFrame",4,1],"584":["res/bullet16/6/texture",3,1],"585":["res/bullet16/6/spriteFrame",4,1],"586":["res/bullet10200/ww6/texture",3,1],"587":["res/bullet10200/ww6/spriteFrame",4,1],"588":["res/bullet10200/ww10/texture",3,1],"589":["res/bullet10200/ww10/spriteFrame",4,1],"590":["res/bullet10170/texture",3,1],"591":["res/bullet10170/spriteFrame",4,1],"592":["bullet1082",0],"593":["res/bullet4/texture",3,1],"594":["res/bullet4/spriteFrame",4,1],"595":["res/bullet1044/ddd2/texture",3,1],"596":["res/bullet1044/ddd2/spriteFrame",4,1],"597":["bullet15",0],"598":["res/bullet10200/ww7/texture",3,1],"599":["res/bullet10200/ww7/spriteFrame",4,1],"600":["res/bullet10200/ww4/texture",3,1],"601":["res/bullet10200/ww4/spriteFrame",4,1],"602":["bullet1021",0],"603":["res/bullet21/jgq-b 10/texture",3,1],"604":["res/bullet21/jgq-b 10/spriteFrame",4,1],"605":["bullet10170",0],"606":["res/bullet2/texture",3,1],"607":["res/bullet2/spriteFrame",4,1],"608":["res/bullet20/jgq-a 1/texture",3,1],"609":["res/bullet20/jgq-a 1/spriteFrame",4,1],"610":["res/bullet10180/s4/texture",3,1],"611":["res/bullet10180/s4/spriteFrame",4,1],"612":["res/bullet10130/texture",3,1],"613":["res/bullet10130/spriteFrame",4,1],"614":["res/bullet21/jgq-b 12/texture",3,1],"615":["res/bullet21/jgq-b 12/spriteFrame",4,1],"616":["res/bullet21/jgq-b 03/texture",3,1],"617":["res/bullet21/jgq-b 03/spriteFrame",4,1],"618":["res/bullet1052/skeleton-3 08/texture",3,1],"619":["res/bullet1052/skeleton-3 08/spriteFrame",4,1],"620":["res/bullet1082/sd-huang-1 07/texture",3,1],"621":["res/bullet1082/sd-huang-1 07/spriteFrame",4,1],"622":["res/tail1/texture",3,1],"623":["res/tail1/spriteFrame",4,1],"624":["bullet17",0],"625":["res/bullet1042/huo-5 08/texture",3,1],"626":["res/bullet1042/huo-5 08/spriteFrame",4,1],"627":["res/bullet1104/texture",3,1],"628":["res/bullet1104/spriteFrame",4,1],"629":["res/bullet1082/sd-huang-1 04/texture",3,1],"630":["res/bullet1082/sd-huang-1 04/spriteFrame",4,1],"631":["bullet6",0],"632":["res/bullet8/1/texture",3,1],"633":["res/bullet8/1/spriteFrame",4,1],"634":["res/bullet1082/sd-huang-1 10/texture",3,1],"635":["res/bullet1082/sd-huang-1 10/spriteFrame",4,1],"636":["res/bullet1054/skeleton-4 13/texture",3,1],"637":["res/bullet1054/skeleton-4 13/spriteFrame",4,1],"638":["bullet1061",0],"639":["res/bullet1054/skeleton-4 04/texture",3,1],"640":["res/bullet1054/skeleton-4 04/spriteFrame",4,1],"641":["res/bullet1044/bullet1044",1],"642":["res/bullet20/jgq-a 5/texture",3,1],"643":["res/bullet20/jgq-a 5/spriteFrame",4,1],"644":["res/bullet20/bullet20",1],"645":["bullet1052",0],"646":["res/bullet1054/skeleton-4 12/texture",3,1],"647":["res/bullet1054/skeleton-4 12/spriteFrame",4,1]},"scenes":{},"packs":{"01a1c8659":["279","286","456","559","633"],"01ea73c33":["24","25","26","27","28","29","30","31","280","281","283","284","47","287","288","289","50","49","48","297","298","17","51","57","18","62","63","64","65","73","20","83","84","89","91","93","94","92","95","96","105","106","107","108","23","117","118","119","120","122","137","138","139","140","35","36","37","249","253","254","42","44","45","46","54","55","56","59","61","67","69","75","76","82","98","99","103","112","115","116","127","130","132","32","34","242","41","43","53","58","66","74","77","78","80","22","101","110","123","124","128","131","133","135","33","252","257","39","260","264","275","60","79","81","85","86","88","100","111","126","129","38","40","52","71","72","113","125","68","70","21","97","102","114","134","261","274","19","87","251","109","141","145","146","143","142","144","148","147","149","150","151","158","161","152","155","153","159","160","157","154","156","162","163","164","166","165","167","168","169","171","170","172","173","175","176","174","177","178","179","181","182","186","187","188","183","185","189","184","190","191","192","193","195","199","194","197","196","200"],"0219915ad":["233","244","277","422","540","554","611"],"02bc49aab":["269","293","401","407","417","438","462","510","513","619"],"0306cc690":["271","309","330","397","104","472","635"],"04af92fa9":["211","213","326","328","332","350","355","371","373","391","405","434","537","581","604","615","617"],"04f8fa2b5":["248","323","341","387","403","444","464","572","585"],"04fd8f778":["237","256","436","489","573"],"07a21daa9":["218","529"],"07def267d":["291","418","505"],"0a1a24613":["204","305","316","368","564","180","637","640","647"],"0a2017d08":["348","412","446","450","520","530","568"],"0a90ec573":["219","221","223","225","227","229","231","234","685","686","687","688","285","689","690","691","295","292","290","692","693","201","300","315","203","327","329","331","333","358","207","381","384","398","400","404","406","402","408","411","431","433","435","437","214","455","458","460","463","465","498","500","502","504","243","245","247","674","677","678","268","272","276","278","308","310","312","320","325","338","345","363","365","379","416","419","429","445","451","453","478","484","488","236","240","673","266","270","306","317","335","361","367","370","374","212","424","441","469","471","480","486","490","495","238","676","679","258","680","682","684","322","372","376","386","390","396","421","443","476","482","255","262","304","349","351","447","473","342","347","210","414","427","449","492","681","683","205","393","675","439","506","516","519","512","509","514","523","521","525","528","531","548","555","534","541","536","550","553","546","539","544","557","561","563","567","565","571","575","577","582","580","584","586","590","593","588","595","598","600","603","606","614","616","618","608","612","620","610","622","625","627","629","634","642","632","639","636","646"],"0aa964105":["220","241","339","428","470","477","501","596","641"],"0b4848268":["394","104","551","621","630"],"0b5af1751":["301","319","334","346","366","452","483","626"],"0bd7ee6a7":["239","385","474","487","491","609","643","644"],"0c277fb22":["273","399","409","430","121","481","499","566"],"0c6a35750":["206","208","215","318","380","415","475","507","562","587","589","599","601"],"0dedf8190":["467","624"],"0e25c4090":["202","222","230","246","259","267","296","321","343","352","362","364","377","382","425","440","442","448","459","461","485","522","524","532","538","547","558","576","578","583","591","594","607","613","623","628"],"0e5df3606":["226","232","395","479","515","526","535","556"],"0ecf44f96":["228","235","263","307","311","336","375","420","432","454","466","511","549"],"0f1b89258":["313","359","121","503"],"0f74329ac":["517","180"]},"versions":{"import":[648,"aea68",649,"70265",650,"cfb0d",651,"b464f",652,"dc6c0",653,"8f851",654,"82e33",655,"dc6a7",209,"84098",656,"f26e7",657,"7e93f",216,"55523",217,"e931e",658,"22cf8",659,"48f69",660,"b3753",661,"72166",662,"00b82",663,"540af",224,"f106a",664,"e992a",665,"9a686",666,"70165",667,"807a0",668,"97000",669,"488cf",670,"f8fc7",671,"c5df0",672,"2d697",0,"47c24",1,"77857",250,"b65a8",265,"87894",282,"94d61",294,"d5c31",299,"582c9",302,"6d2c1",303,"ed607",2,"564f3",314,"f833e",3,"f2e51",324,"e030d",337,"4c41b",340,"83aba",344,"ff418",353,"81e71",354,"f7177",356,"98e34",4,"50a5c",357,"4f7d5",360,"f9774",369,"8af82",378,"5857a",383,"bdbdd",388,"aa919",389,"9d83f",392,"44906",5,"b9285",90,"d03f1",6,"1be52",410,"5c599",413,"96745",423,"022c7",426,"1eb78",7,"73a7a",457,"3130e",468,"00d51",493,"09044",494,"1cc18",496,"0adf7",8,"f8384",497,"542e5",136,"0edaa",9,"0a156",508,"755e7",518,"91ca9",527,"a3095",533,"f8adb",542,"371a8",543,"5245a",545,"6e95d",552,"902a5",560,"daacb",10,"c8478",569,"87027",11,"0052c",570,"f3a41",574,"3d8be",579,"d73b0",12,"88b0d",592,"7ec83",597,"6ea93",602,"fe4a6",13,"ef5ef",14,"994b1",605,"e2f55",15,"12dec",631,"74483",638,"2be30",198,"fd647",16,"0ce9a",645,"1e50e"],"native":[17,"f1ab1",18,"e26d0",19,"ab9b7",20,"8d151",21,"ab37b",22,"ed195",23,"3cf33",24,"0f471",25,"ad110",26,"d06ca",27,"5c07c",28,"3ccb6",29,"dc0e9",30,"612de",31,"17e9f",32,"db50b",33,"0e0ec",34,"7da1d",242,"c12ba",35,"fb33f",36,"8c20a",37,"02e4c",249,"62c42",251,"f2344",252,"c1160",253,"4128e",254,"99bd8",38,"a4b3e",257,"581c1",39,"d9876",260,"2ad39",261,"548e5",40,"eb52d",264,"dc8f0",41,"dc3f9",42,"5fd2b",43,"e3ab9",44,"9f9d8",274,"1b9e9",275,"e6df9",45,"f2b77",46,"a20cd",280,"15105",281,"f1948",283,"e59c2",284,"985e7",47,"41c57",287,"f2cc4",288,"aeacc",289,"8b3eb",48,"ea9df",49,"584c1",50,"8ac00",297,"5ed2d",298,"fac94",51,"befd6",52,"0f8a5",53,"8f6e3",54,"d4cdb",55,"c8443",56,"a788e",57,"920fd",58,"9d05d",59,"882da",60,"b910e",61,"1449f",62,"374e1",63,"86a17",64,"9e8a7",65,"a3aa3",66,"e66ed",67,"6f700",68,"a75f1",69,"4c8bc",70,"04a3e",71,"2a140",72,"64c21",73,"151cd",74,"79198",75,"dcd4f",76,"e2848",77,"84a8b",78,"66f34",79,"c4d2a",80,"531c8",81,"08f29",82,"a4b5a",83,"9064c",84,"a2b8d",85,"bcdc6",86,"64a83",87,"c6f01",88,"9944c",89,"b7890",90,"3ef26",91,"223d7",92,"fae2b",93,"25b5a",94,"c317b",95,"3ed7e",96,"8202f",97,"e2e10",98,"9837d",99,"acf02",100,"706b4",101,"a92ef",102,"95869",103,"ef08d",105,"f0d69",106,"e8266",107,"350d6",108,"1026f",109,"e5a7d",110,"ab181",111,"efff8",112,"7a95a",113,"7dc11",114,"c4645",115,"d8e82",116,"a6be2",117,"5362f",118,"2c3c1",119,"ca3a2",120,"737da",122,"a417d",123,"a5fe3",124,"51a1e",125,"48268",126,"242e9",127,"19c35",128,"9bf92",129,"50074",130,"70d16",131,"50d21",132,"bb3c3",133,"f992d",134,"7968f",135,"4af5a",137,"dc9a7",138,"8b546",139,"c1f09",140,"b3e22",141,"c8bf1",142,"bddba",143,"29046",144,"d4e0f",145,"d0b96",146,"02de0",147,"5ab32",148,"1d3a6",149,"ea15a",150,"bc5c4",151,"86f58",152,"5c07c",153,"e07cd",154,"8fe7c",155,"9afd3",156,"e8741",157,"59682",158,"19e27",159,"75927",160,"f3614",161,"19c35",162,"a51f4",163,"070cb",164,"bd936",165,"52daa",166,"96521",167,"c9d7c",168,"6d220",169,"d3dd7",170,"2fcfc",171,"aba98",172,"a5ab4",173,"72d5f",174,"4d712",175,"4d68d",176,"5ebb9",177,"9b2bd",178,"eb7e6",179,"0ab19",181,"82354",182,"6703d",183,"7d396",184,"77fc9",185,"79cb5",186,"66b47",187,"d780c",188,"70f24",189,"4a528",190,"24d03",191,"dedd4",192,"0e9e5",193,"56c02",194,"6fa52",195,"6b44a",196,"3b9f6",197,"954ef",199,"41106",200,"0b621"]},"redirect":[694,"0",695,"1"],"debug":false,"extensionMap":{".cconb":["0","0","1","1","10","10","11","11","12","12","13","13","136","14","14","15","15","16","16","198","198","2","2","3","3","4","4","5","5","6","6","7","7","8","8","9","9"]},"types":["cc.Prefab","cc.SpriteAtlas","cc.ImageAsset","cc.Texture2D","cc.SpriteFrame","cc.AnimationClip","cc.Asset","sp.SkeletonData"]}