[1,["ecpdLyjvZBwrvm+cedCcQy","26+Yff7DxFEb4UGtFqauZJ","3ajAkWBPRLj7IHkBGp3sjk","5fSD2TL6NJFo/tCJtroFy1","12AcR7r4RBerstyZ+AyfFY","119UTApSRF/rqUWgLpWK4k","2ebVUR+bNDZ4OIxaeXF7vd","b9ptxTXqxBCYJgNj1hEHa6","a1LLfUJoxEzYvbMLyDcFSr","5bL+HWb1ZLJr0abp4fFmYU"],["node","_spriteFrame","animationComp","colliderComp","exclamationMark","_textureSetter","root","data"],[["cc.Node",["_name","_components","_prefab","_contentSize","_parent","_children","_trs"],2,9,4,5,1,2,7],["cc.Sprite",["_sizeMode","_isTrimmedMode","node","_materials","_spriteFrame"],1,1,3,6],["cc.Node",["_name","_parent","_components","_prefab","_trs","_children"],2,1,12,4,7,2],"cc.SpriteFrame",["cc.Prefab",["_name"],2],["2b37fzKCGBJh6tkVqx53B+r",["audioOnStart","targetNum","successDelay","failDelay","audioOnStartLoop","node"],-2,1],["408c023jb1IzLshm34P4pGK",["achievementTargetNumber","node"],2,1],["cc.PrefabInfo",["fileId","root"],2,1],["65fb6zdVSFA3INXWLU1edQT",["isTarget","isAchievementTarget","withReaction","alarmedSpeed","normalAniName","deadAniName","node","animationComp","allCllider"],-3,1,1,2],["c598bex1b5PqIk/XYYBbxst",["node","observing","exclamationMark"],3,1,2,6],["3c86chC635BYbDIbq604P9G",["zIndex","isTarget","isAchievementTarget","withReaction","normalSpeed","normalAniName","deadAniName","normalStayAniName","stayFullTime2","moveOffsetX","node","animationComp","allCllider"],-7,1,1,2],["379b9JKlQpIN79jn8YyHUGM",["node","colliderComp"],3,1,1],["a0cd2cUJPdCmbxj2Cs2Ar/s",["zIndex","node"],2,1],["cc.CircleCollider",["_radius","node"],2,1],["cc.Animation",["node","_clips"],3,1,3]],[[7,0,1,2],[0,0,4,1,2,3,2],[2,0,1,5,2,3,4,2],[2,0,1,2,3,4,2],[9,0,1,2,1],[11,0,1,1],[1,0,1,2,3,4,3],[13,0,1,2],[14,0,1,1],[4,0,2],[0,0,5,1,2,3,2],[0,0,4,1,2,3,6,2],[5,0,1,2,3,4,5,6],[6,0,1,2],[8,0,1,2,3,4,5,6,7,8,7],[10,0,1,2,3,4,5,6,7,8,9,10,11,12,11],[1,0,2,3,4,2],[1,2,3,4,1],[12,0,1,2]],[[[{"name":"mansion_1024","rect":[0,0,1024,1024],"offset":[0,0],"originalSize":[1024,1024],"capInsets":[0,0,0,0]}],[3],0,[0],[5],[4]],[[[9,"MapLevel_34"],[10,"mapLevel_34",[-4,-5,-6,-7],[[12,6,2,2,2,false,-2],[13,2,-3]],[0,"acduUFTbRD9pzXhwjfRbmc",-1],[5,1024,1024]],[2,"role_common copy",1,[-14,-15],[[-8,[14,true,true,false,4,54,5,-11,-10,[-9]],[4,-13,[-12],12]],1,4,4],[0,"65gpVTMR5PGKzYmlQFWi2c",1],[-230.639,-250,0,0,0,0,1,1,1,1]],[2,"role_common",1,[-21,-22],[[-16,[15,10,true,true,false,-1.5,92,2,54,2,600,-19,-18,[-17]],[4,-20,[2],11]],1,4,4],[0,"bahP7aXJBA4JmoAIr8rokS",1],[-400,-250,0,0,0,0,1,-1,1,1]],[3,"collider",2,[[-23,[5,-25,-24]],1,4],[0,"27ujwgUzNHmb90qJFyGWCk",1],[-9.604,34.239,0,0,0,0,1,1,1,1]],[3,"collider",3,[[-26,[5,-28,-27]],1,4],[0,"e9G7oxdNpMWIHe+Ny0Hd/+",1],[-9.604,34.239,0,0,0,0,1,1,1,1]],[11,"window_frame",1,[[16,0,-29,[13],14],[18,1001,-30]],[0,"49cHjvXPpGD7rmA0hsAoa3",1],[5,1450,1488],[-4,2,0,0,0,0,1,1,1,1]],[1,"mansion_1024",1,[[17,-31,[0],1]],[0,"55CxxOtDhBzayt0eazEtbu",1],[5,1024,1024]],[1,"man",2,[[6,0,false,-32,[2],3]],[0,"b2AYpAYGJOTqB58VltnNsU",1],[5,129,129]],[7,12,4],[8,2,[4,5]],[1,"man",3,[[6,0,false,-33,[6],7]],[0,"2d9qo8dH5I9KzVeb5caKcj",1],[5,129,129]],[7,12,5],[8,3,[8,9,10]]],0,[0,6,1,0,0,1,0,0,1,0,-1,7,0,-2,2,0,-3,3,0,-4,6,0,-1,10,0,-1,4,0,2,10,0,0,2,0,-1,3,0,0,2,0,-1,8,0,-2,4,0,-1,13,0,-1,5,0,2,13,0,0,3,0,0,3,0,-1,11,0,-2,5,0,-1,9,0,3,9,0,0,4,0,-1,12,0,3,12,0,0,5,0,0,6,0,0,6,0,0,7,0,0,8,0,0,11,0,7,1,33],[0,0,0,0,0,0,0,0,0,0,0,0,0,0,0],[-1,1,-1,1,-1,-2,-1,1,-1,-2,-3,4,4,-1,1],[0,5,0,1,2,6,0,1,2,7,8,3,3,0,9]]]]