[{"__type__":"cc.SpriteFrame","content":{"name":"squareDi","texture":"db/66MI5ZDwaV+D3eZZk8V","rect":[0,0,371,376],"offset":[0,0],"originalSize":[371,376],"capInsets":[69,62,75,56]}},{"__type__":"cc.SpriteFrame","content":{"name":"prefabLoding","texture":"16da6aBjNPnqQBZmRpcMZj","rect":[0,0,177,287],"offset":[0,0],"originalSize":[177,287],"capInsets":[0,0,0,0]}},{"__type__":"cc.SpriteFrame","content":{"name":"showNodeKuang","texture":"06X610A25KZ6fBgswUnmoy","rect":[0,0,371,376],"offset":[0,0],"originalSize":[371,376],"capInsets":[0,0,0,0]}},[{"__type__":"cc.Prefab","_name":"moveChange2","data":{"__id__":1}},{"__type__":"cc.Node","_name":"squareDi","_children":[{"__id__":2},{"__id__":3}],"_level":1,"_components":[{"__type__":"cc.Sprite","node":{"__id__":1},"_spriteFrame":{"__uuid__":"3dRjxbcrtMlYaROShjE0c0"}},{"__type__":"cc.BoxCollider","node":{"__id__":1},"_size":{"__type__":"cc.Size","width":280,"height":280}},{"__type__":"58f08uMhS9NFKF6KHHox0sR","node":{"__id__":1}}],"_prefab":{"__type__":"cc.PrefabInfo","root":{"__id__":1},"asset":{"__uuid__":"ccHCPHurFF2qsMwC8rE1SA"},"fileId":"57iStNMlpLs5ccckCra0RM"},"_contentSize":{"__type__":"cc.Size","width":371,"height":376},"_position":{"__type__":"cc.Vec3","x":793,"y":399},"groupIndex":1},{"__type__":"cc.Node","_name":"showNode","_parent":{"__id__":1},"_level":2,"_components":[{"__type__":"cc.Sprite","node":{"__id__":2},"_spriteFrame":{"__uuid__":"6dKWsGhyBF5YZ9+mp8GIJJ"}}],"_prefab":{"__type__":"cc.PrefabInfo","root":{"__id__":1},"asset":{"__uuid__":"ccHCPHurFF2qsMwC8rE1SA"},"fileId":"91mcxLTcVJyZLCEcDAYRow"},"_contentSize":{"__type__":"cc.Size","width":177,"height":287}},{"__type__":"cc.Node","_name":"showNodeKuang","_parent":{"__id__":1},"_level":2,"_components":[{"__type__":"cc.Sprite","node":{"__id__":3},"_spriteFrame":{"__uuid__":"7fl75a2WpCK4W5amDBhzV6"}},{"__type__":"58f08uMhS9NFKF6KHHox0sR","node":{"__id__":3}}],"_prefab":{"__type__":"cc.PrefabInfo","root":{"__id__":1},"asset":{"__uuid__":"ccHCPHurFF2qsMwC8rE1SA"},"fileId":"49rLm3dWFMe6xbnLtwHWuJ"},"_color":{"__type__":"cc.Color","r":136,"g":16,"b":16},"_contentSize":{"__type__":"cc.Size","width":371,"height":376}}]]