[1,["7c5iv8wBtEN67QJJu1sDYl@6c48a","78UQqHT6tLUb19tqTcE2XS","59TUjkIxtJyLJNfwS2xMui","09ZdI8Lx9PLJPLQILBXDj2@6c48a","11EwB1duJPP5jvEC4zH8ka@6c48a","b9dcZ85kVB1ZSbr227xfbQ@f9941","e6gqPhxTVGVaL4gFFM2Fs3@f9941","6aF1y62VdHkq83TSQ1giSP@f9941","beReEu1qFBSq3vJ+tPJpsi@f9941","48JnE4sKNK3pCX6NmLS9+N@f9941","a9p8XcqtlH+KdADUJE1AtK@f9941","11EwB1duJPP5jvEC4zH8ka@f9941","d3fYNjw5xBFbwJ2HNECMIk@f9941","09ZdI8Lx9PLJPLQILBXDj2@f9941","c6Cpi1er1MJ4gLVE5hzuJF@f9941","f55tXyNeRDY4zObgjbdstQ@f9941","fcEhlIs+RIDruZx0622Sp5@f9941","baITebpKtAXqji00fgy19g@f9941","6dQGpYBcFHwKytLgPxD9Gc@f9941","9d3hObOH1LvJr41f6IDdPP@f9941","5dEIPzJ+FIK6uogBB2ZB9R@f9941","6c01/QsT1EBZVfAt2kcTFc@f9941","48JnE4sKNK3pCX6NmLS9+N@6c48a","5dEIPzJ+FIK6uogBB2ZB9R@6c48a","6aF1y62VdHkq83TSQ1giSP@6c48a","6c01/QsT1EBZVfAt2kcTFc@6c48a","6dQGpYBcFHwKytLgPxD9Gc@6c48a","d1NGQ2rJZCcbhjH0/erZWw","9d3hObOH1LvJr41f6IDdPP@6c48a","a9p8XcqtlH+KdADUJE1AtK@6c48a","b9dcZ85kVB1ZSbr227xfbQ@6c48a","baITebpKtAXqji00fgy19g@6c48a","beReEu1qFBSq3vJ+tPJpsi@6c48a","c6Cpi1er1MJ4gLVE5hzuJF@6c48a","d3fYNjw5xBFbwJ2HNECMIk@6c48a","e6gqPhxTVGVaL4gFFM2Fs3@6c48a","f55tXyNeRDY4zObgjbdstQ@6c48a","fcEhlIs+RIDruZx0622Sp5@6c48a"],["node","_textureSource","_spriteFrame","_particleSystem","_mainTexture","root","data","_defaultClip","mainTexture","_effectAsset"],["cc.SpriteFrame",["cc.CurveRange",["mode","constantMax","constantMin","constant","spline"],-1,4],["cc.Node",["_name","_layer","_components","_prefab","_parent","_children","_lpos"],1,9,4,1,2,5],["cc.UITransform",["node","__prefab","_contentSize","_anchorPoint"],3,1,4,5,5],["cc.GradientRange",["_mode","colorMin","colorMax","gradient"],2,5,5,4],["cc.AlphaKey",["alpha","time"],1],["cc.VelocityOvertimeModule",["_enable","x","y","z","speedModifier"],2,4,4,4,4],["cc.Prefab",["_name"],2],["cc.Node",["_name","_layer","_parent","_components","_prefab","_lpos","_lrot","_euler"],1,1,12,4,5,5,5],["cc.CompPrefabInfo",["fileId"],2],["cc.Animation",["playOnLoad","node","__prefab","_clips","_defaultClip"],2,1,4,3,6],["cc.PrefabInfo",["fileId","root","asset"],2,1,1],["cc.UIMeshRenderer",["node","__prefab"],3,1,4],["cc.Sprite",["node","__prefab","_spriteFrame"],3,1,4,6],["cc.ParticleSystem",["_prewarm","node","__prefab","_materials","startColor","startSizeX","startSizeY","startSizeZ","startSpeed","startRotationX","startRotationY","startRotationZ","startDelay","startLifetime","gravityModifier","rateOverTime","rateOverDistance","_colorOverLifetimeModule","_shapeModule","_sizeOvertimeModule","_velocityOvertimeModule","_forceOvertimeModule","_limitVelocityOvertimeModule","_rotationOvertimeModule","_textureAnimationModule","_trailModule","renderer"],2,1,4,3,4,4,4,4,4,4,4,4,4,4,4,4,4,4,4,4,4,4,4,4,4,4,4],["cc.ColorOvertimeModule",["_enable","color"],2,4],["cc.Gradient",["alphaKeys"],3,9],["cc.ShapeModule",["_enable","_shapeType","arcSpeed","_scale"],1,4,5],["cc.SizeOvertimeModule",["size","x","y","z"],3,4,4,4,4],["cc.ForceOvertimeModule",["x","y","z"],3,4,4,4],["cc.LimitVelocityOvertimeModule",["limitX","limitY","limitZ","limit"],3,4,4,4,4],["cc.RotationOvertimeModule",["_enable","x","y","z"],2,4,4,4],["cc.TextureAnimationModule",["frameOverTime","startFrame"],3,4,4],["cc.RealCurve",["_times","_values"],2,9],["cc.RealKeyframeValue",["interpolationMode","value"],1],["cc.TrailModule",["lifeTime","widthRatio","colorOverTrail","colorOvertime","_particleSystem"],3,4,4,4,4,1],["cc.ParticleSystemRenderer",["_mainTexture"],3,6],["cc.Material",["_techIdx","_states","_defines","_props"],0,12]],[[1,1],[9,0,2],[11,0,1,2,2],[3,0,1,2,1],[13,0,1,2,1],[2,0,1,4,2,3,6,3],[1,3,2],[5,0,1,3],[4,1],[1,0,2,1,4],[24,0,1,3],[8,0,1,2,3,4,5,6,7,3],[12,0,1,1],[14,0,1,2,3,4,5,6,7,8,9,10,11,12,13,14,15,16,17,18,19,20,21,22,23,24,25,26,2],[4,0,1,2,2],[4,0,3,2],[1,0,1,3],[1,0,4,2],[15,0,1,2],[16,0,1],[5,0,2],[17,0,1,2,3,3],[18,0,1,2,3,1],[19,0,1,2,1],[20,0,1,2,3,1],[21,0,1,2,3,2],[22,0,1,1],[23,0,1,2],[25,0,1,2,3,4,1],[26,0,1],[7,0,2],[2,0,1,5,2,3,3],[2,0,1,4,2,3,3],[3,0,1,2,3,1],[3,0,1,1],[10,0,1,2,3,4,2],[6,0,1,2,3,4,2],[6,1,2,3,4,1],[27,0,1,2,3,4]],[[[{"name":"chooseBgBox20","rect":{"x":0,"y":0,"width":576,"height":228},"offset":{"x":0,"y":0},"originalSize":{"width":576,"height":228},"rotated":false,"capInsets":[0,0,0,0],"packable":true}],[0],0,[0],[1],[3]],[[{"name":"chooseBgBox27","rect":{"x":0,"y":0,"width":147,"height":97},"offset":{"x":0,"y":0},"originalSize":{"width":147,"height":97},"rotated":false,"capInsets":[0,0,0,0],"packable":true}],[0],0,[0],[1],[4]],[[[30,"chooseBgBox"],[31,"chooseBgBox",33554432,[-4,-5,-6,-7,-8,-9,-10,-11,-12,-13,-14,-15,-16,-17,-18,-19,-20,-21,-22],[[3,-2,[1,"3c+ahfhjNIALd2odw44/xs"],[5,1280,720]],[35,true,-3,[1,"31MrugnE9EsqIJsheoxsPr"],[21],22]],[2,"07/16Yct5FTaICCq2bX58E",-1,0]],[11,"left",33554432,1,[[-23,[33,-24,[1,"96Dk+JIXhE/ZuYBv4fbPL0"],[5,600,2200],[0,0.5,0]],[12,-25,[1,"c78b0kM3VONqveEZ958eA/"]]],1,4,4],[2,"6dEuBAV+xPOogfOQa0MzK0",1,0],[1,-500,0,0],[3,0,0,-0.7071067811865475,0.7071067811865476],[1,0,0,-90]],[11,"right",33554432,1,[[-26,[34,-27,[1,"365oypW9ZHrL46TOXof1gf"]],[12,-28,[1,"dde4yy2LRLJaD0X3J0+dgN"]]],1,4,4],[2,"d1t6kbPFRANKZGZGFVLvs9",1,0],[1,500,0,0],[3,0.5,0.4999999999999999,0.5,0.5000000000000001],[1,0,89.99999999999999,90]],[32,"chooseBg",33554432,1,[[3,-29,[1,"67mDQ3igdEWrdXIYpRznrY"],[5,1600,720]],[4,-30,[1,"af6SjVXA5L1rTa2yILVWK6"],0]],[2,"d50MLbctpEXaEOmK+RWWW/",1,0]],[5,"chooseBgBox36",33554432,1,[[3,-31,[1,"86euRM+jFDQYnBZ1zzDHhu"],[5,122,130]],[4,-32,[1,"43U7kKWUtFy4t3Yd8lftH7"],5]],[2,"b9YDj/MVxP4LRLIy4QxTCY",1,0],[1,-157.968,90.013,0]],[5,"chooseBgBox34",33554432,1,[[3,-33,[1,"39IsF+WrpEdLySR3qwALQP"],[5,295,421]],[4,-34,[1,"d39Ac78FRP3L/PEn9JEH+p"],6]],[2,"70eBiy6IhAgb4gL29L88Rz",1,0],[1,-216.893,172.348,0]],[5,"chooseBgBox33",33554432,1,[[3,-35,[1,"4d6t3MXalE5ooL5JLteZj/"],[5,267,242]],[4,-36,[1,"d9mMgjE6JA17FJucNcp04L"],7]],[2,"5fa5VLIDlIBaLb0dfQ08/R",1,0],[1,-496.703,-232.499,0]],[5,"chooseBgBox30",33554432,1,[[3,-37,[1,"93GCtxJVtG86Q6bh8HI2wE"],[5,223,204]],[4,-38,[1,"e9vmBsC1ZAzooNklkkdpeK"],8]],[2,"68FsBTlQpHj7HO/mYZKayx",1,0],[1,242.533,55.621,0]],[5,"chooseBgBox28",33554432,1,[[3,-39,[1,"e2fo9ZpCNMsbmIcuNSquGO"],[5,413,355]],[4,-40,[1,"22QJEVln5I+Lz689ImQAy/"],9]],[2,"d1o5CC/DNFIq6OXb47ARz2",1,0],[1,558.653,267.228,0]],[5,"chooseBgBox27",33554432,1,[[3,-41,[1,"98Oyn9jPhE+r26wY8pm5C8"],[5,147,97]],[4,-42,[1,"9bcoukSLdMqJxRoPpkKCZb"],10]],[2,"b2d8n7vcNEeIlUn+sGXMF5",1,0],[1,-110.489,-75.403,0]],[5,"chooseBgBox24",33554432,1,[[3,-43,[1,"f7TUAmCC9Ktboc3v48ZX2T"],[5,172,137]],[4,-44,[1,"07yXO7cD5Cv7R/kFYp9fLd"],11]],[2,"fdfw2rTvVNpqwCxraVUn/+",1,0],[1,-17.74,261.315,0]],[5,"chooseBgBox20",33554432,1,[[3,-45,[1,"b9EC3qIMdCqqlzLxG+S8/a"],[5,576,228]],[4,-46,[1,"4akt/SPSNAd4xoI9AIxxQZ"],12]],[2,"70HrzcMNFEj6rXiszAhn46",1,0],[1,-454.171,248.772,0]],[5,"chooseBgBox18",33554432,1,[[3,-47,[1,"85Aax+TUNHwLjT3T9aKFJZ"],[5,230,196]],[4,-48,[1,"53YmdTkN5L1rbJ/0xgav/5"],13]],[2,"b6oUrRTMlNrbseq/MKB23a",1,0],[1,400.175,-30.681,0]],[5,"chooseBgBox17",33554432,1,[[3,-49,[1,"beUVhcL3hDZZ0xOCdE25Es"],[5,286,225]],[4,-50,[1,"a2vU3T9V9LT758wqtGBV/c"],14]],[2,"77Faif0KtENbIeOF5bVF0M",1,0],[1,510.059,-248.034,0]],[5,"chooseBgBox12",33554432,1,[[3,-51,[1,"91k7kFnTlFJLt3VGYDTaVm"],[5,667,157]],[4,-52,[1,"8aYmzl6CZNtY32mwEc8Pqd"],15]],[2,"86iKUBPupIW6hYbSYjwkWS",1,0],[1,20.832,-146.42,0]],[5,"chooseBgBox10",33554432,1,[[3,-53,[1,"91DKrMOyNL1q81qYE30dLU"],[5,415,111]],[4,-54,[1,"79osdoG5tAyo5274ali7Bw"],16]],[2,"72XaSHOBhImKtXOSCghfYj",1,0],[1,-25.165,-178.487,0]],[5,"chooseBgBox09",33554432,1,[[3,-55,[1,"21mDBg2J5A6ZD+L2qaQ9lY"],[5,578,147]],[4,-56,[1,"19SUDJiZRFtb3SzXf15NWZ"],17]],[2,"5bSdJd0ZdHdLdkPf+AjQ85",1,0],[1,29.302,217.287,0]],[5,"chooseBgBox05",33554432,1,[[3,-57,[1,"24fM5guWtOXYIXBeOL3It1"],[5,504,583]],[4,-58,[1,"afyfLUQSBMEJb5BcPRvLUq"],18]],[2,"24s7BqVNdNzJ5k0X4joUfc",1,0],[1,-511.866,34.85,0]],[5,"chooseBgBox02",33554432,1,[[3,-59,[1,"05QMDKfAJIebTcCgw03jC7"],[5,235,519]],[4,-60,[1,"d99hHA+eVHb4nY3I2t8oyh"],19]],[2,"f7yRgI/MhI7KJGJOkq65Rz",1,0],[1,626.892,100.706,0]],[5,"chooseBgBox01",33554432,1,[[3,-61,[1,"4f08hCcC1F56qdvyvpIl0C"],[5,993,182]],[4,-62,[1,"6awIjoFH9Pj7iVWEDbEn5y"],20]],[2,"c6i8LZ7QlHGLpu3gLyABUj",1,0],[1,16.649,-270.095,0]],[13,true,2,[1,"12n1Rny0lMpovqsU74E8lR"],[1],[14,2,[4,4292769791],[4,4294928060]],[9,3,5,15],[0],[0],[0],[0],[0],[16,3,6.283185307179586],[0],[6,16],[0],[6,0.8],[0],[18,true,[15,1,[19,[[20,0],[7,60,0.3],[7,60,0.7],[7,0,1]]]]],[21,true,0,[6,1],[1,400,1,1]],[22,[0],[0],[0],[0]],[36,true,[0],[9,3,60,30],[0],[6,1]],[23,[0],[0],[0]],[24,[0],[0],[0],[0]],[25,true,[0],[0],[6,1.0471975511965976]],[26,[17,1,[27,[0,1],[[10,2,1],[10,2,1]]]],[0]],[28,[6,1],[0],[8],[8],-63],[29,2]],[13,true,3,[1,"49OI1vGmdK7rhpJlRD9OIs"],[3],[14,2,[4,4292769791],[4,4294928060]],[9,3,5,15],[0],[0],[9,3,30,60],[0],[0],[16,3,6.283185307179586],[0],[6,16],[0],[6,0.8],[0],[18,true,[15,1,[19,[[20,0],[7,60,0.3],[7,60,0.7],[7,0,1]]]]],[21,true,0,[6,1],[1,400,1,1]],[22,[0],[0],[0],[0]],[37,[0],[0],[0],[6,1]],[23,[0],[0],[0]],[24,[0],[0],[0],[0]],[25,true,[0],[0],[6,-1.0471975511965976]],[26,[17,1,[27,[0,1],[[10,2,1],[10,2,1]]]],[0]],[28,[6,1],[0],[8],[8],-64],[29,4]]],0,[0,5,1,0,0,1,0,0,1,0,-1,4,0,-2,2,0,-3,3,0,-4,5,0,-5,6,0,-6,7,0,-7,8,0,-8,9,0,-9,10,0,-10,11,0,-11,12,0,-12,13,0,-13,14,0,-14,15,0,-15,16,0,-16,17,0,-17,18,0,-18,19,0,-19,20,0,-1,21,0,0,2,0,0,2,0,-1,22,0,0,3,0,0,3,0,0,4,0,0,4,0,0,5,0,0,5,0,0,6,0,0,6,0,0,7,0,0,7,0,0,8,0,0,8,0,0,9,0,0,9,0,0,10,0,0,10,0,0,11,0,0,11,0,0,12,0,0,12,0,0,13,0,0,13,0,0,14,0,0,14,0,0,15,0,0,15,0,0,16,0,0,16,0,0,17,0,0,17,0,0,18,0,0,18,0,0,19,0,0,19,0,0,20,0,0,20,0,3,21,0,3,22,0,6,1,64],[0,0,0,0,0,0,0,0,0,0,0,0,0,0,0,0,0,0,0,0,0,0,0],[2,-1,4,-1,4,2,2,2,2,2,2,2,2,2,2,2,2,2,2,2,2,-1,7],[5,1,0,1,0,6,7,8,9,10,11,12,13,14,15,16,17,18,19,20,21,2,2]],[[{"name":"chooseBgBox30","rect":{"x":0,"y":0,"width":223,"height":204},"offset":{"x":0,"y":0},"originalSize":{"width":223,"height":204},"rotated":false,"capInsets":[0,0,0,0],"packable":true}],[0],0,[0],[1],[22]],[[{"name":"chooseBgBox02","rect":{"x":0,"y":0,"width":235,"height":519},"offset":{"x":0,"y":0},"originalSize":{"width":235,"height":519},"rotated":false,"capInsets":[0,0,0,0],"packable":true}],[0],0,[0],[1],[23]],[[{"name":"chooseBgBox34","rect":{"x":0,"y":0,"width":295,"height":421},"offset":{"x":0,"y":0},"originalSize":{"width":295,"height":421},"rotated":false,"capInsets":[0,0,0,0],"packable":true}],[0],0,[0],[1],[24]],[[{"name":"chooseBgBox01","rect":{"x":0,"y":0,"width":993,"height":182},"offset":{"x":0,"y":0},"originalSize":{"width":993,"height":182},"rotated":false,"capInsets":[0,0,0,0],"packable":true}],[0],0,[0],[1],[25]],[[{"name":"chooseBgBox09","rect":{"x":0,"y":0,"width":578,"height":147},"offset":{"x":0,"y":0},"originalSize":{"width":578,"height":147},"rotated":false,"capInsets":[0,0,0,0],"packable":true}],[0],0,[0],[1],[26]],[[[38,"1",[{"rasterizerState":{},"depthStencilState":{},"blendState":{"targets":[{}]}}],[{}],[[[{},"mainTexture",6,0]],11]]],0,0,[0,0],[8,9],[0,27]],[[{"name":"chooseBgBox05","rect":{"x":0,"y":0,"width":504,"height":583},"offset":{"x":0,"y":0},"originalSize":{"width":504,"height":583},"rotated":false,"capInsets":[0,0,0,0],"packable":true}],[0],0,[0],[1],[28]],[[{"name":"chooseBgBox28","rect":{"x":0,"y":0,"width":413,"height":355},"offset":{"x":0,"y":0},"originalSize":{"width":413,"height":355},"rotated":false,"capInsets":[0,0,0,0],"packable":true}],[0],0,[0],[1],[29]],[[{"name":"chooseBg","rect":{"x":0,"y":0,"width":1600,"height":720},"offset":{"x":0,"y":0},"originalSize":{"width":1600,"height":720},"rotated":false,"capInsets":[0,0,0,0],"packable":true}],[0],0,[0],[1],[30]],[[{"name":"chooseBgBox10","rect":{"x":0,"y":0,"width":415,"height":111},"offset":{"x":0,"y":0},"originalSize":{"width":415,"height":111},"rotated":false,"capInsets":[0,0,0,0],"packable":true}],[0],0,[0],[1],[31]],[[{"name":"chooseBgBox33","rect":{"x":0,"y":0,"width":267,"height":242},"offset":{"x":0,"y":0},"originalSize":{"width":267,"height":242},"rotated":false,"capInsets":[0,0,0,0],"packable":true}],[0],0,[0],[1],[32]],[[{"name":"chooseBgBox18","rect":{"x":0,"y":0,"width":230,"height":196},"offset":{"x":0,"y":0},"originalSize":{"width":230,"height":196},"rotated":false,"capInsets":[0,0,0,0],"packable":true}],[0],0,[0],[1],[33]],[[{"name":"chooseBgBox24","rect":{"x":0,"y":0,"width":172,"height":137},"offset":{"x":0,"y":0},"originalSize":{"width":172,"height":137},"rotated":false,"capInsets":[0,0,0,0],"packable":true}],[0],0,[0],[1],[34]],[[{"name":"chooseBgBox36","rect":{"x":0,"y":0,"width":122,"height":130},"offset":{"x":0,"y":0},"originalSize":{"width":122,"height":130},"rotated":false,"capInsets":[0,0,0,0],"packable":true}],[0],0,[0],[1],[35]],[[{"name":"chooseBgBox17","rect":{"x":0,"y":0,"width":286,"height":225},"offset":{"x":0,"y":0},"originalSize":{"width":286,"height":225},"rotated":false,"capInsets":[0,0,0,0],"packable":true}],[0],0,[0],[1],[36]],[[{"name":"chooseBgBox12","rect":{"x":0,"y":0,"width":667,"height":157},"offset":{"x":0,"y":0},"originalSize":{"width":667,"height":157},"rotated":false,"capInsets":[0,0,0,0],"packable":true}],[0],0,[0],[1],[37]]]]
