[1,["95NKJyrxlFobiNk3XDKxG4","6e/KaKSNJChbqczXrcXEIb"],["_textureSetter","spriteFrame"],["cc.SpriteFrame",["cc.BitmapFont",["_name","fontSize","_fntConfig"],0]],[[1,0,1,2,4]],[[[{"name":"font40_bold_0","rect":[0,0,256,256],"offset":[0,0],"originalSize":[256,256],"capInsets":[0,0,0,0]}],[0],0,[0],[0],[0]],[[[0,"font40_bold",40,{"commonHeight":40,"fontSize":40,"atlasName":"font40_bold_0.png","fontDefDictionary":{"48":{"xOffset":1,"yOffset":4,"xAdvance":22,"rect":{"x":124,"y":50,"width":30,"height":39}},"49":{"xOffset":2,"yOffset":5,"xAdvance":12,"rect":{"x":115,"y":90,"width":19,"height":38}},"50":{"xOffset":1,"yOffset":4,"xAdvance":21,"rect":{"x":155,"y":50,"width":28,"height":39}},"51":{"xOffset":2,"yOffset":4,"xAdvance":21,"rect":{"x":184,"y":50,"width":28,"height":39}},"52":{"xOffset":0,"yOffset":4,"xAdvance":22,"rect":{"x":92,"y":50,"width":31,"height":39}},"53":{"xOffset":2,"yOffset":5,"xAdvance":21,"rect":{"x":58,"y":96,"width":28,"height":38}},"54":{"xOffset":1,"yOffset":4,"xAdvance":20,"rect":{"x":213,"y":49,"width":28,"height":39}},"55":{"xOffset":2,"yOffset":5,"xAdvance":20,"rect":{"x":87,"y":96,"width":27,"height":38}},"56":{"xOffset":2,"yOffset":4,"xAdvance":21,"rect":{"x":0,"y":99,"width":28,"height":39}},"57":{"xOffset":1,"yOffset":4,"xAdvance":20,"rect":{"x":29,"y":99,"width":28,"height":39}},"120":{"xOffset":0,"yOffset":11,"xAdvance":19,"rect":{"x":135,"y":90,"width":29,"height":32}},"20851":{"xOffset":0,"yOffset":1,"xAdvance":39,"rect":{"x":0,"y":50,"width":48,"height":48}},"20998":{"xOffset":0,"yOffset":1,"xAdvance":39,"rect":{"x":0,"y":0,"width":49,"height":49}},"21345":{"xOffset":0,"yOffset":1,"xAdvance":39,"rect":{"x":50,"y":0,"width":49,"height":49}},"26368":{"xOffset":0,"yOffset":2,"xAdvance":39,"rect":{"x":199,"y":0,"width":49,"height":48}},"26631":{"xOffset":0,"yOffset":1,"xAdvance":39,"rect":{"x":100,"y":0,"width":49,"height":49}},"30446":{"xOffset":4,"yOffset":3,"xAdvance":39,"rect":{"x":49,"y":50,"width":42,"height":45}},"39640":{"xOffset":0,"yOffset":1,"xAdvance":39,"rect":{"x":150,"y":0,"width":48,"height":49}},"65306":{"xOffset":7,"yOffset":11,"xAdvance":39,"rect":{"x":165,"y":90,"width":16,"height":32}},"-1":{"xOffset":0,"yOffset":39,"xAdvance":0,"rect":{"x":242,"y":49,"width":10,"height":11}}},"kerningDict":{}}]],0,0,[0],[1],[1]]]]